Workbook

Sheet Version
B3: Version | C3: Detail | D3: start date
B4: 1 | C4: Create test scenario & test case based from FRS only. | D4: 46118
B5: 2 | C5: Update test scenario & test case based from demo | D5: 46127

Sheet Todo List
K4: TestCase
M5: UserAccountAccess&Validation | N5: Only Add TC title need to complete the rest
M6: Search
M7: Product Comparison
M8: AddToCart
M9: WishList
M10: Checkout | N10: blocked on payment method
M11: AccountFeature
M12: Footer Feature
K16: Defect | N16: Need formatting
N17: Need to add details,picture reference on defect

Sheet Defect
A4: Defect ID | B4: Detected Date | C4: Description/Summary | D4: Step to Reproduce | E4: Expected Result | F4: Actual Result | G4: Severity | H4: Priority | I4: Screenshot | J4: Status
A5: Def-001 | B5: =DATE(2026,4,20) -> 46132 | C5: frequently 522 response | D5: 1. open application URL | E5: User enter homepage | F5: 522 error | G5: Critical | H5: P0 (High) | I5: =_xlfn.DISPIMG("ID_DCD6BF44FE934B62BEF4AF54A6DF501A",1) -> =DISPIMG("ID_DCD6BF44FE934B62BEF4AF54A6DF501A",1) | J5: Occasionaly occurs
A6: Def-002 | B6: =DATE(2026,4,20) -> 46132 | C6: All product is out of stock | D6: 1. open application URL 2. add product to cart 3. proceed to checkout 4. set quantity to 1 or more 5. click checkout | E6: proceed to checkout page | F6: no single item available to proceed | G6: low | H6: P0 (High) | I6: =_xlfn.DISPIMG("ID_BA59952DF61247A7B7CF088F37895BD1",1) -> =DISPIMG("ID_BA59952DF61247A7B7CF088F37895BD1",1) | J6: fixed
A7: Def-003 | B7: 46132 | C7: Need letter limitation | D7: 1. open application URL 2. Input long text to search tab 3. click search | E7: should not accept long input which can cause stress to server | F7: Always accept user input and conduct searches, but occasionally limit the search function for a set time period. | G7: low | H7: low | J7: found
A8: Def-004 | B8: 46135 | C8: No payment available | D8: 1. open application 2. login 3. add product to cart 4. check out 5. select payment method | E8: have selectable list of payment method available | F8: got error message,no available payment method can not continue transaction | G8: Critical | H8: P0 (High) | I8: =_xlfn.DISPIMG("ID_5AE021B245F644E3960B009A03D090E8",1) -> =DISPIMG("ID_5AE021B245F644E3960B009A03D090E8",1) | J8: found
A9: Def-005 | B9: 46135 | C9: nothing happen after click choose payment method when not logged in | D9: 1. open application 2. add product to cart 3. check out 4. select payment method | E9: have selectable list of payment method available | F9: not thing happen | G9: high | H9: P0 (High) | I9: =_xlfn.DISPIMG("ID_D5E4F8FF524944B6A0BD069F07AF88C0",1) -> =DISPIMG("ID_D5E4F8FF524944B6A0BD069F07AF88C0",1) | J9: found
A10: Def-006 | B10: 46135 | C10: when added out of stock item to cart on wish list + show error message | D10: 1. open application 2. add out of stock product to wish list 3. open wish list page 4. click add to cart button on added product | E10: should not be able product to cart / not shown error message | F10: successfully added product to cart and have error message appear

Sheet RTM
A1: Traceablility Matrix
A6: Req. ID | B6: Req Desc | C6: Scenario | D6: TC ID | E6: TC Desc | F6: Test Result | G6: Defect Id | H6: Defect Status

Sheet Scenario
A1: Open Cart Frontend
A2: URL | B2: https://demo.opencart.com/
A3: Requirement | B3: https://drive.google.com/drive/folders/1nBs25k9jTb06qrV-5fTC75gtPOR6uW4V
B4: * 1.0 create test scenario/test case only from FRS only
A9: Test Scenario ID | B9: Reference | C9: Test Scenario Description | D9: Priority | E9: Number of Test Cases | F9: defect | G9: Note
A10: TS001 | B10: Demo | C10: Validate the working of 'Register an account' functionality | D10: P0 | E10: =COUNTIF('UserAccountAccess&Validation'!B:B,"*TS001*") -> 26 | F10: =COUNTIFS('UserAccountAccess&Validation'!J:J,"defect",'UserAccountAccess&Validation'!B:B,"%TS001%") -> 0
A11: TS002 | B11: Demo | C11: Validate the working of 'Login' functionality | D11: P0 | E11: =COUNTIF('UserAccountAccess&Validation'!B:B,"*TS002*") -> 15 | F11: =COUNTIFS('UserAccountAccess&Validation'!J:J,"defect",'UserAccountAccess&Validation'!B:B,"%TS002%") -> 0
A12: TS003 | B12: Demo | C12: Validate the working of 'Logout' functionality | D12: P0 | E12: =COUNTIF('UserAccountAccess&Validation'!B:B,"*TS003*") -> 2 | F12: =COUNTIFS('UserAccountAccess&Validation'!J:J,"defect",'UserAccountAccess&Validation'!B:B,"%TS003%") -> 0
A13: TS004 | B13: Demo | C13: Validate the working of 'Forgot Password' functionality | D13: P2 | E13: =COUNTIF('UserAccountAccess&Validation'!B:B,"*TS004*") -> 7 | F13: =COUNTIFS('UserAccountAccess&Validation'!J:J,"defect",'UserAccountAccess&Validation'!B:B,"%TS004%") -> 0
A14: TS005 | B14: FRS | C14: Validate the working of 'Search' functionality | D14: P1 | E14: =COUNTIF(Search!B:B,"*TS005*") -> 23 | F14: =COUNTIF(Search!J3:J10006,"Defect") -> 0
A15: TS006 | B15: FRS | C15: Validate the working of 'Product compare' functionality | D15: P2 | E15: =COUNTIF('Product Comparison'!B:B,"*TS006*") -> 7 | F15: =COUNTIF('Product Comparison'!J3:J9999,"Defect") -> 0
A16: TS007 | B16: FRS | C16: Validate the working of 'Product page' functionality | D16: P1 | E16: =COUNTIF('Product Pages'!B2:B201,"*TS007*") -> 30 | F16: =COUNTIF('Product Pages'!J2:J9998,"Defect") -> 0
A17: TS008 | B17: FRS | C17: Validate the working of 'Add to cart' functionality | D17: P1 | E17: =COUNTA(AddToCart!A3:A202) -> 10 | F17: =COUNTIF(AddToCart!J3:J9999,"Defect") -> 1
A18: TS009 | B18: FRS | C18: Validate the working of 'Wish List' option | D18: P4 | E18: =COUNTA(WishList!B:B) -> 11 | F18: =COUNTIF(WishList!J1:J10004,"Defect") -> 2
A19: TS010 | B19: FRS | C19: Validate the working of 'Shopping Cart page' functionality | D19: P1 | E19: =COUNTA('Shopping Cart page'!A1:A1007) -> 36 | F19: =COUNTIF('Shopping Cart page'!J2:J9998,"Defect") -> 0
A20: TS011 | B20: FRS | C20: Validate the working of 'Home page' functionality | D20: P2 | E20: =COUNTA(HomePage!A2:A9997) -> 11 | F20: =COUNTIF(HomePage!J2:J9998,"Defect") -> 0
A21: TS012 | B21: FRS | C21: Validate the working of 'Checkout' functionality | D21: P1 | E21: =COUNTA(Checkout!A2:A10052) -> 66 | F21: =COUNTIF(Checkout!J2:J10052,"defect") -> 0
A22: TS013 | B22: Demo | C22: Validate the working of 'My Account' functionality | D22: P3 | E22: =COUNTIF(UserFeature!B:B,"*TS013*") -> 2
A23: TS014 | B23: Demo | C23: Validate the working of 'My Account > Account Information' functionality | D23: P3 | E23: =COUNTIF(UserFeature!B:B,"*TS014*") -> 19
A24: TS015 | B24: Demo | C24: Validate the working of 'My Account > Change Password' functionality | D24: P3 | E24: =COUNTIF(UserFeature!B:B,"*TS015*") -> 17
A25: TS016 | B25: Demo | C25: Validate the working of 'My Account Address Book' functionality | D25: P3 | E25: =COUNTIF(UserFeature!B:B,"*TS016*") -> 66
A26: TS017 | B26: Demo | C26: Validate the working of 'My Order > Order History' functionality | D26: P3
A27: TS018 | B27: Demo | C27: Validate the working of 'My Orders > Order Information' functionality | D27: P3
A28: TS019 | B28: Demo | C28: Validate the working of 'My Orders > Product Returns' functionality | D28: P3
A29: TS020 | B29: Demo | C29: Validate the working of 'My Order > Downloads' functionality | D29: P3
A30: TS021 | B30: Demo | C30: Validate the working of 'My Orders > Reward Points' functionality | D30: P3
A31: TS022 | B31: Demo | C31: Validate the working of 'My Orders > Returned Request' functionality | D31: P3
A32: TS023 | B32: Demo | C32: Validate the working of 'My Order > Your Transactions' functionality | D32: P3
A33: TS024 | B33: Demo | C33: Validate the working of 'My Order > Recurring Payments' functionality | D33: P3
A34: TS025 | B34: FRS | C34: Validate the working of 'Affiliate' functionality | D34: P4
A35: TS026 | B35: FRS | C35: Validate the working of 'Newsletter' functionality | D35: P4
A36: TS027 | B36: FRS | C36: Validate the working of 'Contact Us' functionality | D36: P4
A37: TS028 | B37: FRS | C37: Validate the working of 'Gift' functionality | D37: P4
A38: TS029 | B38: FRS | C38: Validate the working of 'Special Offer' functionality | D38: P4
A39: TS030 | B39: FRS | C39: Validate the working of 'Header' options' functionality | D39: P4 | E39: =COUNTA(Header!A2:A204) -> 26 | F39: =COUNTIF(Header!J2:J10003,"Defect") -> 0
A40: TS031 | B40: FRS | C40: Validate the working of 'Top Menu' options' functionality | D40: P4 | E40: =COUNTA('Top Menu'!A2:A200) -> 5 | F40: =COUNTIF('Top Menu'!J2:J9998,"defect") -> 0
A41: TS032 | B41: FRS | C41: Validate the working of 'Footer' options' functionality | D41: P4 | E41: =COUNTA(Footer!A2:A199) -> 16 | F41: =COUNTIF(Footer!J2:J9998,"defect") -> 0
A42: TS033 | B42: FRS | C42: Validate the Application functionality for different currency | D42: P2 | E42: =COUNTA(Currency!A2:A199) -> 2 | F42: =COUNTIF(Currency!J2:J9998,"defect") -> 0
D43: Total = | E43: =SUM(E10:E42) -> 397

Sheet UserAccountAccess&Validation
A1: Test Case ID | B1: Test Scenario | C1: Test Case Title | D1: Pre-requisites | E1: Test Steps | F1: Test Data | G1: Expected Result (ER) | H1: Actual Result | I1: Priority | J1: Result | K1: Comments
A2: TC_ACC_001 | B2: =_xlfn.TEXTJOIN(CHAR(10),,Scenario!A11,Scenario!C11) -> TS002 Validate the working of 'Login' functionality | C2: Validate login - structure | D2: Open application, enter login page | E2: 1. Validate result (ER-1) | F2: Not applicable | G2: Page should contain header,new customer section,login section, account sub-menu section
A3: TC_ACC_002 | B3: =_xlfn.TEXTJOIN(CHAR(10),,Scenario!A11,Scenario!C11) -> TS002 Validate the working of 'Login' functionality | C3: Validate user - access - header | D3: Open application,On any page of the application | E3: 1. Click my account on header 2. Click Login button 3. Validate result (ER-1) | F3: Not applicable | G3: Should redirect user to account page
A4: TC_ACC_003 | B4: =_xlfn.TEXTJOIN(CHAR(10),,Scenario!A11,Scenario!C11) -> TS002 Validate the working of 'Login' functionality | C4: Validate login - access - check out | D4: Open application, added item to cart, proceed to checkout, not logged in | E4: 1. Click 'check out' button 2. Validate result (ER-1) 3. Click login link on message 4. Validate result (ER-2) | F4: Not applicable | G4: 1. Should show message "please login or create an account before continue" 2. Should redirect user to account page
A5: TC_ACC_004 | B5: =_xlfn.TEXTJOIN(CHAR(10),,Scenario!A11,Scenario!C11) -> TS002 Validate the working of 'Login' functionality | C5: Validate login - access - wish list | D5: Open application,not logged in | E5: 1. Select item to add to wish list -<Refer test data> 2. Validate message (ER-1) 3. Click login link on message 4. Validate result (ER-2) | F5: Product : iMac | G5: 1. Should show message "You must login or create an account to save "iMac" to your wish list! " 2. Should redirect user to login page
A6: TC_ACC_005 | B6: =_xlfn.TEXTJOIN(CHAR(10),,Scenario!A11,Scenario!C11) -> TS002 Validate the working of 'Login' functionality | C6: Validate Login - email required field | D6: Open application, enter login page | E6: 1. Click 'log in' button 2. Validate result (ER-1),(ER-2) | F6: Not applicable | G6: 1. Should not accept input and return with warning "Warning : please enter an email" 2. should show " * " symbol after text "email" | H6: Accept null data and continue the process Result in " Warning: No match for E-Mail Address and/or Password." Have correct symbol shown
A7: TC_ACC_006 | B7: =_xlfn.TEXTJOIN(CHAR(10),,Scenario!A11,Scenario!C11) -> TS002 Validate the working of 'Login' functionality | C7: Validate Login - email valid | D7: Open application, enter login page | E7: 1. Enter an email -<Refer test data> 2. Click 'log in' button 3. Validate result (ER-1) | F7: email : test@gmail.com | G7: Should accept test data and check with backend
A8: TC_ACC_007 | B8: =_xlfn.TEXTJOIN(CHAR(10),,Scenario!A11,Scenario!C11) -> TS002 Validate the working of 'Login' functionality | C8: Validate Login - email wrong format | D8: Open application, enter login page | E8: 1. enter an email -<Refer test data> 2. Click 'log in' button 3. Validate result (ER-1) | F8: email: test_gmail.com | G8: Should not accept data and return with warning | H8: Accept data and continue the process
A9: TC_ACC_008 | B9: =_xlfn.TEXTJOIN(CHAR(10),,Scenario!A11,Scenario!C11) -> TS002 Validate the working of 'Login' functionality | C9: Validate Login - email boundary - below | D9: Open application, enter login page | E9: 1. enter an email -<Refer test data> 2. Click 'log in' button 3. Validate result (ER-1) | F9: email : any input that below 4 characters | G9: accept when input is at least 6 characters | H9: Accept data and continue the process | K9: Should only accept 4-20 characters input
A10: TC_ACC_009 | B10: =_xlfn.TEXTJOIN(CHAR(10),,Scenario!A11,Scenario!C11) -> TS002 Validate the working of 'Login' functionality | C10: Validate Login - email boundary - above | D10: Open application, enter login page | E10: 1. enter an email -<Refer test data> 2. Click 'log in' button 3. Validate result (ER-1) | F10: email : any input that over 255 characters | G10: do not accept when input is over 254 characters input | H10: Accept data and continue the process | K10: Should only accept 4-20 characters input
A11: TC_ACC_010 | B11: =_xlfn.TEXTJOIN(CHAR(10),,Scenario!A12,Scenario!C12) -> TS003 Validate the working of 'Logout' functionality | C11: Validate Login - password required field | D11: Open application, enter login page | E11: 1. Click 'log in' button 2. Validate result (ER-1) | F11: Not applicable | G11: Should not accept input and return with warning "Warning : please enter a password" | H11: Accept null data and continue the process Result in " Warning: No match for E-Mail Address and/or Password."
A12: TC_ACC_011 | B12: =_xlfn.TEXTJOIN(CHAR(10),,Scenario!A11,Scenario!C11) -> TS002 Validate the working of 'Login' functionality | C12: Validate Login - password valid | D12: Open application, enter login page | E12: 1. Enter password -<Refer test data> 2. Click 'log in' button 3. Validate result (ER-1) | F12: password : test | G12: Should accept the password
A13: TC_ACC_012 | B13: =_xlfn.TEXTJOIN(CHAR(10),,Scenario!A11,Scenario!C11) -> TS002 Validate the working of 'Login' functionality | C13: Validate Login - password invalid | D13: Open application, enter login page | E13: 1. Enter password -<Refer test data> 2. Click 'log in' button 3. Validate result (ER-1) | F13: password : รหัสผ่าน | G13: Should not accept the password and return with warning "Warning: No match for E-Mail Address and/or Password." | H13: Did not accept the password and return correct warning
A14: TC_ACC_013 | B14: =_xlfn.TEXTJOIN(CHAR(10),,Scenario!A11,Scenario!C11) -> TS002 Validate the working of 'Login' functionality | C14: Validate Login - password boundary - below | D14: Open application, enter login page | E14: 1. Enter password -<Refer test data> 2. Click 'log in' button 3. Validate result (ER-1) | F14: password : pas | G14: Should not accept the password but still return with warning "Warning: No match for E-Mail Address and/or Password." | H14: Did not accept the password and return correct warning
A15: TC_ACC_014 | B15: =_xlfn.TEXTJOIN(CHAR(10),,Scenario!A11,Scenario!C11) -> TS002 Validate the working of 'Login' functionality | C15: Validate Login - password boundary - above | D15: Open application, enter login page | E15: 1. Enter password -<Refer test data> 2. Click 'log in' button 3. Validate result (ER-1) | F15: password : any mixed characters that over 50 characters | G15: Should not accept the password but still return with warning "Warning: No match for E-Mail Address and/or Password." | H15: Did not accept the password and return correct warning
A16: TC_ACC_015 | B16: =_xlfn.TEXTJOIN(CHAR(10),,Scenario!A11,Scenario!C11) -> TS002 Validate the working of 'Login' functionality | C16: Validate Login - pass | D16: Open application, enter login page | E16: 1. Enter email&password -<Refer test data> 2. Click 'log in' button 3. Validate result (ER-1) | F16: email : test@gmail.com password : test | G16: User should redirect to user page
A17: TC_ACC_016 | B17: =_xlfn.TEXTJOIN(CHAR(10),,Scenario!A11,Scenario!C11) -> TS002 Validate the working of 'Login' functionality | C17: Validate Login - fail | D17: Open application, enter login page | E17: 1. Enter email&password -<Refer test data> 2. Click 'log in' button 3. Validate result (ER-1) | F17: email : test@gmail.com password : test1234 | G17: Should fail the login and return with warning "Warning: No match for E-Mail Address and/or Password." | H17: Did not pass the login and return with correct warning
A18: TC_ACC_017 | B18: =_xlfn.TEXTJOIN(CHAR(10),,Scenario!$A$10,Scenario!$C$10) -> TS001 Validate the working of 'Register an account' functionality | C18: Validate Register - access - header | D18: Open application, enter register page | E18: 1. Click my account on header 2. Click register button 3. Validate result (ER-1) | F18: Not applicable | G18: Should redirect user to register page
A19: TC_ACC_018 | B19: =_xlfn.TEXTJOIN(CHAR(10),,Scenario!$A$10,Scenario!$C$10) -> TS001 Validate the working of 'Register an account' functionality | C19: Validate Register - access - wish list | D19: Open application,not logged in | E19: 1. Select item to add to wish list -<Refer test data> 2. Validate message (ER-1) 3. Click register link on message 4. Validate result (ER-2) | F19: Product : iMac | G19: 1. Should show message "You must login or create an account to save "iMac" to your wish list! " 2. Should redirect user to login page
A20: TC_ACC_019 | B20: =_xlfn.TEXTJOIN(CHAR(10),,Scenario!$A$10,Scenario!$C$10) -> TS001 Validate the working of 'Register an account' functionality | C20: Validate Register - access - check out | D20: Open application, added item to cart, proceed to checkout, not logged in | E20: 1. Click 'check out' button 2. Validate result (ER-1) | F20: Not applicable | G20: Should redirect user to register page
A21: TC_ACC_020 | B21: =_xlfn.TEXTJOIN(CHAR(10),,Scenario!$A$10,Scenario!$C$10) -> TS001 Validate the working of 'Register an account' functionality | C21: Validate Register - page structure | D21: Open application, enter register page | E21: 1. Validate result (ER-1) | F21: Not applicable | G21: Page should contain these element : Firstname, lastname, email,password,newsletter subscribtion,privacy policy agreement continue button
A22: TC_ACC_021 | B22: =_xlfn.TEXTJOIN(CHAR(10),,Scenario!$A$10,Scenario!$C$10) -> TS001 Validate the working of 'Register an account' functionality | C22: Validate Register - first name - required field | D22: Open application, enter register page | E22: 1. Click continue 2. Validate result (ER-1) | F22: Not applicable | G22: Should show error message "Please enter your first name" under first name field. first name fieldhave " * " mark at the end of first name
A23: TC_ACC_022 | B23: =_xlfn.TEXTJOIN(CHAR(10),,Scenario!$A$10,Scenario!$C$10) -> TS001 Validate the working of 'Register an account' functionality | C23: Validate Register - first name - valid | D23: Open application, enter register page | E23: 1. Enter first name -<Refer test data> 2. Click continue 3. Validate result | F23: first name : sawan | G23: Should accept first name and not show any error under first name field
A24: TC_ACC_023 | B24: =_xlfn.TEXTJOIN(CHAR(10),,Scenario!$A$10,Scenario!$C$10) -> TS001 Validate the working of 'Register an account' functionality | C24: Validate Register - first name - boundary - below | D24: Open application, enter register page | E24: 1. Enter first name -<Refer test data> 2. Click continue 3. Validate result | F24: first name : s | G24: Should not accept first name and show message "first name should be between 4 and 20 characters"
A25: TC_ACC_024 | B25: =_xlfn.TEXTJOIN(CHAR(10),,Scenario!$A$10,Scenario!$C$10) -> TS001 Validate the working of 'Register an account' functionality | C25: Validate Register - first name - boundary - above | D25: Open application, enter register page | E25: 1. Enter first name -<Refer test data> 2. Click continue 3. Validate result | F25: first name : any name that over 20 characters | G25: Should not accept first name and show message "first name should be between 4 and 20 characters"
A26: TC_ACC_025 | B26: =_xlfn.TEXTJOIN(CHAR(10),,Scenario!$A$10,Scenario!$C$10) -> TS001 Validate the working of 'Register an account' functionality | C26: Validate Register - first name - not support characters | D26: Open application, enter register page | E26: 1. Enter first name -<Refer test data> 2. Click continue 3. Validate result | F26: first name : s@wan | G26: Should not accept first name and show message "first name should contain only english characters"
A27: TC_ACC_026 | B27: =_xlfn.TEXTJOIN(CHAR(10),,Scenario!$A$10,Scenario!$C$10) -> TS001 Validate the working of 'Register an account' functionality | C27: Validate Register - last name - require field | D27: Open application, enter register page | E27: 1. Click continue 2. Validate result (ER-1) | F27: Not applicable | G27: Should show error message "Please enter your last name" Under last name fieldhave " * " mark at the end of last name
A28: TC_ACC_027 | B28: =_xlfn.TEXTJOIN(CHAR(10),,Scenario!$A$10,Scenario!$C$10) -> TS001 Validate the working of 'Register an account' functionality | C28: Validate Register - last name - valid | D28: Open application, enter register page | E28: 1. Enter last name -<Refer test data> 2. Click continue 3. Validate result (ER-1) | F28: last name : sumartara | G28: Should accept last name and not show any error message
A29: TC_ACC_028 | B29: =_xlfn.TEXTJOIN(CHAR(10),,Scenario!$A$10,Scenario!$C$10) -> TS001 Validate the working of 'Register an account' functionality | C29: Validate Register - last name - boundary - below | D29: Open application, enter register page | E29: 1. Enter last name -<Refer test data> 2. Click continue 3. Validate result (ER-1) | F29: last name : any name under 4 characters | G29: Should not accept last name under 4 characters
... A43: TC_ACC_043 | B43: =_xlfn.TEXTJOIN(CHAR(10),,Scenario!$A$10,Scenario!$C$10) -> TS001 Validate the working of 'Register an account' functionality | C43: Validate Register - duplicate | D43: Open application, enter login page | E43: 1. Enter all required information 2. Click checkbox 3. Click continue | F43: email : test@gmail.com password : aa1234 | G43: Should successfully register an account,show message "Your email has already used to create and account if you forgot your password please reset password"
A44: TC_ACC_044 | B44: =_xlfn.TEXTJOIN(CHAR(10),,Scenario!A12,Scenario!C12) -> TS003 Validate the working of 'Logout' functionality | C44: Validate user can logout | D44: Open applicationuser already logged in | E44: 1. Click my account on header 2. Click Log out button 3. Validate result (ER-1) | F44: Not applicable | G44: User should logged out
A45: TC_ACC_045 | B45: =_xlfn.TEXTJOIN(CHAR(10),,Scenario!A13,Scenario!C13) -> TS004 Validate the working of 'Forgot Password' functionality | C45: Validate Login - forgot password | D45: Open application, enter login page | E45: 1. Click 'forgot password' button 2. Validate result (ER-1) | F45: Not applicable | G45: User should redirect to reset password page | H45: User edirect to reset password page
A46: TC_ACC_046 | B46: =_xlfn.TEXTJOIN(CHAR(10),,Scenario!A13,Scenario!C13) -> TS004 Validate the working of 'Forgot Password' functionality | C46: Validate Login - forgot password sturcture | D46: Open application, enter reset password page | E46: 1. Validate result (ER-1) | F46: Not applicable | G46: Page should contain header,account sub-menu section, input email for resetting password, go back button,continue button
A47: TC_ACC_047 | B47: =_xlfn.TEXTJOIN(CHAR(10),,Scenario!A13,Scenario!C13) -> TS004 Validate the working of 'Forgot Password' functionality | C47: Validate Login - forgot password successful | D47: Open application, enter reset password page | E47: 1. enter an email -<Refer test data> 2. Click 'continue button 3. Validate result (ER-1) | F47: email : test@gmail.com | G47: Should return message "Resetting password link was sent to your email."
A48: TC_ACC_048 | B48: =_xlfn.TEXTJOIN(CHAR(10),,Scenario!A13,Scenario!C13) -> TS004 Validate the working of 'Forgot Password' functionality | C48: Validate Login - forgot password invalid email | D48: Open application, enter reset password page | E48: 1. enter an email -<Refer test data> 2. Click 'continue button 3. Validate result (ER-1) | F48: email : เทส_gmail.com | G48: Should return message "Please enter valid email"
A49: TC_ACC_049 | B49: =_xlfn.TEXTJOIN(CHAR(10),,Scenario!A13,Scenario!C13) -> TS004 Validate the working of 'Forgot Password' functionality | C49: Validate Login - forgot password required field email | D49: Open application, enter reset password page | E49: 1. Click 'continue button 2. Validate result (ER-1) | F49: Not applicable | G49: Should return message "Please enter an email" have * mark next to email as in "email*"
A50: TC_ACC_050 | B50: =_xlfn.TEXTJOIN(CHAR(10),,Scenario!A13,Scenario!C13) -> TS004 Validate the working of 'Forgot Password' functionality | C50: Validate Login - forgot password not exists email | D50: Open application, enter reset password page | E50: 1. enter an email -<Refer test data> 2. Click 'continue button 3. Validate result (ER-1) | F50: email : test3@gmail.com | G50: Should return message "This email is not registered with this application"
A51: TC_ACC_051 | B51: =_xlfn.TEXTJOIN(CHAR(10),,Scenario!A13,Scenario!C13) -> TS004 Validate the working of 'Forgot Password' functionality | C51: Validate Login - forgot password go back button | D51: Open application, enter reset password page | E51: 1. click "back" button 2. Validate result (ER-1) | F51: Not applicable | G51: Should return to login page

Sheet UserFeature
A1: Test Case ID | B1: Test Scenario | C1: Test Case Title | D1: Pre-requisites | E1: Test Steps | F1: Test Data | G1: Expected Result (ER) | H1: Actual Result | I1: Priority | J1: Result | K1: Comments
A2: TC_ACF_001 | B2: =_xlfn.TEXTJOIN(CHAR(10),,Scenario!$A$22,Scenario!$C$22) -> TS013 Validate the working of 'My Account' functionality | C2: Validate account features | D2: Open application,logged in | E2: 1. Click 'my account' on header 2. Click 'my account' option 3. Validate result (Validate ER-1) | F2: Not applicable | G2: Account page should have following function by section : My Account : edit account information, change password, modify address book entries, modify wish list My Orders : view order history, subscribtion, downlaods,reward points,return request, transaction My Affiliate Account : register for affiliate account News letter : subscribe/unsubscibe Shortcut for quick access on all listed features on right side
A3: TC_ACF_002 | B3: =_xlfn.TEXTJOIN(CHAR(10),,Scenario!$A$22,Scenario!$C$22) -> TS013 Validate the working of 'My Account' functionality | C3: Validate quick access features | D3: Open application,logged in,location is on any account page | E3: 1. Validate result (Validate ER-1) | F3: Not applicable | G3: Should show quick access on right side of the page for navigate through account features
A4: TC_ACF_003 | B4: =_xlfn.TEXTJOIN(CHAR(10),,Scenario!$A$23,Scenario!$C$23) -> TS014 Validate the working of 'My Account > Account Information' functionality | C4: Validate account information link - main | D4: Open application,logged in,enter my account page | E4: 1. Click 'edit your account information' link below my account 2. Validate result (Validate ER-1) | F4: Not applicable | G4: Should navigate user to account information page
A5: TC_ACF_004 | B5: =_xlfn.TEXTJOIN(CHAR(10),,Scenario!$A$23,Scenario!$C$23) -> TS014 Validate the working of 'My Account > Account Information' functionality | C5: Validate account information link - quick access | D5: Open application,logged in,location is on any account page | E5: 1. Click 'edit your account information' link on quick access 2. Validate result (Validate ER-1) | F5: Not applicable | G5: Should navigate user to account information page
A6: TC_ACF_005 | B6: =_xlfn.TEXTJOIN(CHAR(10),,Scenario!$A$23,Scenario!$C$23) -> TS014 Validate the working of 'My Account > Account Information' functionality | C6: Validate account information - element | D6: Open application,logged in,location is on account information page | E6: 1. Validate result (Validate ER-1) | F6: Not applicable | G6: This page should show user current information. User can edit information : first name, last name, email include back and confirmation button at buttom
A7: TC_ACF_006 | B7: =_xlfn.TEXTJOIN(CHAR(10),,Scenario!$A$23,Scenario!$C$23) -> TS014 Validate the working of 'My Account > Account Information' functionality | C7: Validate account information - current information | D7: Open application,logged in,location is on account information page | E7: 1. Validate result (Validate ER-1) | F7: Not applicable | G7: Current information first name, last name and email address should show correctly
A8: TC_ACF_007 | B8: =_xlfn.TEXTJOIN(CHAR(10),,Scenario!$A$23,Scenario!$C$23) -> TS014 Validate the working of 'My Account > Account Information' functionality | C8: Validate account information - required field visibility | D8: Open application,logged in,location is on account information page | E8: 1. Validate result (Validate ER-1) | F8: Not applicable | G8: Should have shown " * " mark for first name, last name and email
A9: TC_ACF_008 | B9: =_xlfn.TEXTJOIN(CHAR(10),,Scenario!$A$23,Scenario!$C$23) -> TS014 Validate the working of 'My Account > Account Information' functionality | C9: Validate account information - required field functionality | D9: Open application,logged in,location is on account information page | E9: 1. Empty input field -<Refer test data> 2. Click continue 3. Validate result (Validate ER-1) | F9: Field : first name, last name, email address | G9: The deleted field should show message "This field should not be empty"
A10: TC_ACF_009 | B10: =_xlfn.TEXTJOIN(CHAR(10),,Scenario!$A$23,Scenario!$C$23) -> TS014 Validate the working of 'My Account > Account Information' functionality | C10: Validate account information - data modification first name valid | D10: Open application,logged in,location is on account information page | E10: 1. Change text in first name -<Refer test data> 2. Click continue 3. Validate result (Validate ER-1) | F10: First name : John | G10: First name should change to input data
A11: TC_ACF_010 | B11: =_xlfn.TEXTJOIN(CHAR(10),,Scenario!$A$23,Scenario!$C$23) -> TS014 Validate the working of 'My Account > Account Information' functionality | C11: Validate account information - data modification first name invalid characters | D11: Open application,logged in,location is on account information page | E11: 1. Change text in first name -<Refer test data> 2. Click continue 3. Validate result (Validate ER-1) | F11: First name : จอห์น | G11: Only accept english which contain between 1 - 32 characters Show error message "Please use only english characters for first name"
A12: TC_ACF_011 | B12: =_xlfn.TEXTJOIN(CHAR(10),,Scenario!$A$23,Scenario!$C$23) -> TS014 Validate the working of 'My Account > Account Information' functionality | C12: Validate account information - data modification first name invalid size | D12: Open application,logged in,location is on account information page | E12: 1. Change text in first name -<Refer test data> 2. Click continue 3. Validate result (Validate ER-1) | F12: First name : J , name that over 20 characters | G12: Show message "First Name must be between 1 and 32 characters!"
A13: TC_ACF_012 | B13: =_xlfn.TEXTJOIN(CHAR(10),,Scenario!$A$23,Scenario!$C$23) -> TS014 Validate the working of 'My Account > Account Information' functionality | C13: Validate account information - data modification last name valid | D13: Open application,logged in,location is on account information page | E13: 1. Change text in last name -<Refer test data> 2. Click continue 3. Validate result (Validate ER-1) | F13: Last name : Rowel | G13: Last name should change to input data
A14: TC_ACF_013 | B14: =_xlfn.TEXTJOIN(CHAR(10),,Scenario!$A$23,Scenario!$C$23) -> TS014 Validate the working of 'My Account > Account Information' functionality | C14: Validate account information - data modification last name invalid characters | D14: Open application,logged in,location is on account information page | E14: 1. Change text in last name -<Refer test data> 2. Click continue 3. Validate result (Validate ER-1) | F14: Last name : กำเนิด | G14: Only accept english which contain between 1 - 20 characters Show error message "Please use only english characters for last name"
A15: TC_ACF_014 | B15: =_xlfn.TEXTJOIN(CHAR(10),,Scenario!$A$23,Scenario!$C$23) -> TS014 Validate the working of 'My Account > Account Information' functionality | C15: Validate account information - data modification last name invalid size | D15: Open application,logged in,location is on account information page | E15: 1. Change text in last name -<Refer test data> 2. Click continue 3. Validate result (Validate ER-1) | F15: Last name : B , name that over 20 characters | G15: Show message "Last Name must be between 1 and 32 characters!"
... A22: TC_ACF_021 | B22: =_xlfn.TEXTJOIN(CHAR(10),,Scenario!$A$23,Scenario!$C$23) -> TS014 Validate the working of 'My Account > Account Information' functionality | C22: Validate login after user change email address - old email | D22: Open application,logged in,location is on account information page | E22: 1. Change email -<Refer test data> 2. Logout 3. Try to login with old email | F22: New email : John.new@gmail.com Old email : John@gmail.com | G22: Should fail the login and return with warning "Warning:This email was changed from the account please use new email to login"
A23: TC_ACF_022 | B23: =_xlfn.TEXTJOIN(CHAR(10),,Scenario!$A$24,Scenario!$C$24) -> TS015 Validate the working of 'My Account > Change Password' functionality | C23: Validate change password feature - access through account page | D23: Open application,logged in,location is on account information page | E23: 1. Click change your password link under my account section 2. Validate result (Validate ER-1) | F23: Not applicable | G23: Should navigate user to change password page
A24: TC_ACF_023 | B24: =_xlfn.TEXTJOIN(CHAR(10),,Scenario!$A$24,Scenario!$C$24) -> TS015 Validate the working of 'My Account > Change Password' functionality | C24: Validate change password feature - access through quick access | D24: Open application,logged in,location is on any account page | E24: 1. Click password on quick access 2. Validate result (Validate ER-1) | F24: Not applicable | G24: Should navigate user to change password page
A25: TC_ACF_024 | B25: =_xlfn.TEXTJOIN(CHAR(10),,Scenario!$A$24,Scenario!$C$24) -> TS015 Validate the working of 'My Account > Change Password' functionality | C25: Validate change password feature - element | D25: Open application,logged in,location is on change password page | E25: 1. Validate result (Validate ER-1) | F25: Not applicable | G25: Page should show page title "Change Password" have 2 input password and password confirm, back button and continue button
A26: TC_ACF_025 | B26: =_xlfn.TEXTJOIN(CHAR(10),,Scenario!$A$24,Scenario!$C$24) -> TS015 Validate the working of 'My Account > Change Password' functionality | C26: Validate change password feature - required field | D26: Open application,logged in,location is on change password page | E26: 1. Leave password and password confirm empty 2. Click confirm button 3. Validate result (Validate ER-1) | F26: Not applicable | G26: Password and password confirm should has visible "*" mark and did not accept empty input
A27: TC_ACF_026 | B27: =_xlfn.TEXTJOIN(CHAR(10),,Scenario!$A$24,Scenario!$C$24) -> TS015 Validate the working of 'My Account > Change Password' functionality | C27: Validate change password feature - hidden | D27: Open application,logged in,location is on change password page | E27: 1. Input password and password confirm -<Refer test data> 2. Validate reuslt (Validate ER-1) | F27: Password : 123456 Password confirm : 123456 | G27: Password should be hidden
A28: TC_ACF_027 | B28: =_xlfn.TEXTJOIN(CHAR(10),,Scenario!$A$24,Scenario!$C$24) -> TS015 Validate the working of 'My Account > Change Password' functionality | C28: Validate change password feature - show | D28: Open application,logged in,location is on change password page | E28: 1. Input password and password confirm -<Refer test data> 2. Validate reuslt (Validate ER-1) | F28: Password : 123456 Password confirm : 123456 | G28: Should have visible reveal password button | H28: Do not have reveal password button
A29: TC_ACF_028 | B29: =_xlfn.TEXTJOIN(CHAR(10),,Scenario!$A$24,Scenario!$C$24) -> TS015 Validate the working of 'My Account > Change Password' functionality | C29: Validate change password feature - back button | D29: Open application,logged in,location is on change password page | E29: 1. Click back button 2. Validate reuslt (Validate ER-1) | F29: Not applicable | G29: Should navigate user back to account information page
A30: TC_ACF_029 | B30: =_xlfn.TEXTJOIN(CHAR(10),,Scenario!$A$24,Scenario!$C$24) -> TS015 Validate the working of 'My Account > Change Password' functionality | C30: Validate change password feature - continue button | D30: Open application,logged in,location is on change password page | E30: 1. Click back button 2. Validate reuslt (Validate ER-1) | F30: Not applicable | G30: Should visible and locate on buttom right of the password input location
A31: TC_ACF_030 | B31: =_xlfn.TEXTJOIN(CHAR(10),,Scenario!$A$24,Scenario!$C$24) -> TS015 Validate the working of 'My Account > Change Password' functionality | C31: Validate change password feature - change password match | D31: Open application,logged in,location is on change password page | E31: 1. Input password and password confirm -<Refer test data> 2. Click continue 3. Validate reuslt (Validate ER-1) | F31: Password : 123456 Password confirm : 123456 | G31: Should show message "Password change successfully"
A32: TC_ACF_031 | B32: =_xlfn.TEXTJOIN(CHAR(10),,Scenario!$A$24,Scenario!$C$24) -> TS015 Validate the working of 'My Account > Change Password' functionality | C32: Validate change password feature - change password not match | D32: Open application,logged in,location is on change password page | E32: 1. Input password and password confirm -<Refer test data> 2. Click continue 3. Validate reuslt (Validate ER-1) | F32: Password : 123456 Password confirm : 1234567 | G32: Should show message "Both password does not match"
A33: TC_ACF_032 | B33: =_xlfn.TEXTJOIN(CHAR(10),,Scenario!$A$24,Scenario!$C$24) -> TS015 Validate the working of 'My Account > Change Password' functionality | C33: Validate change password feature - change password same as previous password | D33: Open application,logged in,location is on change password page | E33: 1. Input password and password confirm -<Refer test data> 2. Click continue 3. Validate reuslt (Validate ER-1) | F33: Password : 123456 Password confirm : 123456 | G33: Should show message "You cannot use old password as a new password"
A34: TC_ACF_033 | B34: =_xlfn.TEXTJOIN(CHAR(10),,Scenario!$A$24,Scenario!$C$24) -> TS015 Validate the working of 'My Account > Change Password' functionality | C34: Validate change password feature - change password to password that already use in the past | D34: Open application,logged in,location is on change password page | E34: 1. Input password and password confirm -<Refer test data> 2. Click continue 3. Validate reuslt (Validate ER-1) | F34: Password : 123456 Password confirm : 123456 | G34: Should show message "You cannot use old password as a new password"
A35: TC_ACF_034 | B35: =_xlfn.TEXTJOIN(CHAR(10),,Scenario!$A$24,Scenario!$C$24) -> TS015 Validate the working of 'My Account > Change Password' functionality | C35: Validate change password feature - change password successful | D35: Open application,logged in,location is on change password page | E35: 1. Input password and password confirm -<Refer test data> 2. Click continue 3. Validate reuslt (Validate ER-1) | F35: Password : 54321 Password confirm : 54321 | G35: Should show message "Password change successfully"
A36: TC_ACF_035 | B36: =_xlfn.TEXTJOIN(CHAR(10),,Scenario!$A$24,Scenario!$C$24) -> TS015 Validate the working of 'My Account > Change Password' functionality | C36: Validate change password feature - invalid password | D36: Open application,logged in,location is on change password page | E36: 1. Input password and password confirm -<Refer test data> 2. Click continue 3. Validate reuslt (Validate ER-1) | F36: Password : ฟหกด Password confirm : ฟหกด | G36: Should show message "PLease use only english alphabet,number,special characters as your password"
A37: TC_ACF_036 | B37: =_xlfn.TEXTJOIN(CHAR(10),,Scenario!$A$24,Scenario!$C$24) -> TS015 Validate the working of 'My Account > Change Password' functionality | C37: Validate change password feature - login with new password | D37: Open application,have an account,password changed,not logged in | E37: 1. Login with new password -<Refer test data> 2. Validate result (Validate ER-1) | F37: Email : John@gmail.com Password : 54321 | G37: Should successfully loged in
A38: TC_ACF_037 | B38: =_xlfn.TEXTJOIN(CHAR(10),,Scenario!$A$24,Scenario!$C$24) -> TS015 Validate the working of 'My Account > Change Password' functionality | C38: Validate change password feature - login with old password | D38: Open application,have an account,password changed,not logged in | E38: 1. Login with new password -<Refer test data> 2. Validate result (Validate ER-1) | F38: Email : John@gmail.com Password : 123456 | G38: Should fail the login and return with warning "Warning:This password was changed from the account please use new password or reset password"
A39: TC_ACF_038 | B39: =_xlfn.TEXTJOIN(CHAR(10),,Scenario!$A$24,Scenario!$C$24) -> TS015 Validate the working of 'My Account > Change Password' functionality | C39: Validate change password feature - login with previous password | D39: Open application,have an account,password changed,not logged in | E39: 1. Login with new password -<Refer test data> 2. Validate result (Validate ER-1) | F39: Email : John@gmail.com Password : 123456 | G39: Should fail the login and return with warning "Warning:This password was changed from the account please use new password or reset password"
A40: TC_ACF_039 | B40: =_xlfn.TEXTJOIN(CHAR(10),,Scenario!$A$25,Scenario!$C$25) -> TS016 Validate the working of 'My Account Address Book' functionality | C40: Validate access to address book - access through account page | D40: Open application,logged in,enter my account page | E40: 1. Click 'modify your address entries' under my account section 2. Validate result (Valdate ER-1) | F40: Not applicable
A41: TC_ACF_040 | B41: =_xlfn.TEXTJOIN(CHAR(10),,Scenario!$A$25,Scenario!$C$25) -> TS016 Validate the working of 'My Account Address Book' functionality | C41: Validate access to address book - access through quick access | D41: Open application,logged in,location is on any account page | E41: 1. Click 'Address Book' option on quick access 2. Validate result (Validate ER-1) | F41: Not applicable
A42: TC_ACF_041 | B42: =_xlfn.TEXTJOIN(CHAR(10),,Scenario!$A$25,Scenario!$C$25) -> TS016 Validate the working of 'My Account Address Book' functionality | C42: Address book page - element | D42: Open application,logged in,location is on address book page | E42: 1. Validate result (Validate ER-1) | F42: Not applicable | G42: Should contain "Address Book Entries" header,address book information,back button, new address button, quick access section
A43: TC_ACF_042 | B43: =_xlfn.TEXTJOIN(CHAR(10),,Scenario!$A$25,Scenario!$C$25) -> TS016 Validate the working of 'My Account Address Book' functionality | C43: Address book page - no address | D43: Open application,logged in,location is on address book page,has no entry on the list | E43: 1. Validate result (Validate ER-1) | F43: Not applicable | G43: Should show message "You have no addresses in your account." under address book entities section
A44: TC_ACF_043 | B44: =_xlfn.TEXTJOIN(CHAR(10),,Scenario!$A$25,Scenario!$C$25) -> TS016 Validate the working of 'My Account Address Book' functionality | C44: Address book page - have item | D44: Open application,logged in,location is on address book page,has at least one entry on the list | E44: 1. Validate result (Validate ER-1) | F44: Not applicable | G44: Should shown entries by row, have entries data on left side and action button (edit and delete) on the right side
A45: TC_ACF_044 | B45: =_xlfn.TEXTJOIN(CHAR(10),,Scenario!$A$25,Scenario!$C$25) -> TS016 Validate the working of 'My Account Address Book' functionality | C45: Address book page - back button | D45: Open application,logged in,location is on address book page | E45: 1. Click back button 2. Validate reuslt (Validate ER-1) | F45: Not applicable | G45: Should navigate user back to account information page
A46: TC_ACF_045 | B46: =_xlfn.TEXTJOIN(CHAR(10),,Scenario!$A$25,Scenario!$C$25) -> TS016 Validate the working of 'My Account Address Book' functionality | C46: Address book page - delete address | D46: Open application,logged in,location is on address book page,has at least one entry on the list | E46: 1. Click delete button on entry -<Refer test data> 2. Validate result (Validate ER-1) | F46: Entries : any entries | G46: Selected entry should be removed
A47: TC_ACF_046 | B47: =_xlfn.TEXTJOIN(CHAR(10),,Scenario!$A$25,Scenario!$C$25) -> TS016 Validate the working of 'My Account Address Book' functionality | C47: Address book page - access add address | D47: Open application,logged in,location is on address book page | E47: 1. Click new address button 2. Validate result (Validate ER-1) | F47: Not applicable | G47: Should navigate user to add address page
A48: TC_ACF_047 | B48: =_xlfn.TEXTJOIN(CHAR(10),,Scenario!$A$25,Scenario!$C$25) -> TS016 Validate the working of 'My Account Address Book' functionality | C48: Add address - element | D48: Open application,logged in,location is on add address page | E48: 1. Validate result (Validate ER-1) | F48: Not applicable | G48: Should contain 'Add Address' title, input of : first name, last name, company, address 1, address2, city, post code, country, region/state, default address back button, continue button and quick access tab
A49: TC_ACF_048 | B49: =_xlfn.TEXTJOIN(CHAR(10),,Scenario!$A$25,Scenario!$C$25) -> TS016 Validate the working of 'My Account Address Book' functionality | C49: Add address - required field | D49: Open application,logged in,location is on add address page | E49: 1. Leave required field empty 2. Click continue button 3. Validate result (Validate ER-1) | F49: Field : first name, last name, address, city, post code, country, region/state | G49: required field should has visible red " * " mark, will show error message to put data on required field if leave empty
A50: TC_ACF_049 | B50: =_xlfn.TEXTJOIN(CHAR(10),,Scenario!$A$25,Scenario!$C$25) -> TS016 Validate the working of 'My Account Address Book' functionality | C50: Add address - place holder
A51: TC_ACF_050 | B51: =_xlfn.TEXTJOIN(CHAR(10),,Scenario!$A$25,Scenario!$C$25) -> TS016 Validate the working of 'My Account Address Book' functionality | C51: Add address - selection default
A52: TC_ACF_051 | B52: =_xlfn.TEXTJOIN(CHAR(10),,Scenario!$A$25,Scenario!$C$25) -> TS016 Validate the working of 'My Account Address Book' functionality | C52: Add address - first name - valid
A53: TC_ACF_052 | B53: =_xlfn.TEXTJOIN(CHAR(10),,Scenario!$A$25,Scenario!$C$25) -> TS016 Validate the working of 'My Account Address Book' functionality | C53: Add address - first name - invalid
A54: TC_ACF_053 | B54: =_xlfn.TEXTJOIN(CHAR(10),,Scenario!$A$25,Scenario!$C$25) -> TS016 Validate the working of 'My Account Address Book' functionality | C54: Add address - last name - valid
A55: TC_ACF_054 | B55: =_xlfn.TEXTJOIN(CHAR(10),,Scenario!$A$25,Scenario!$C$25) -> TS016 Validate the working of 'My Account Address Book' functionality | C55: Add address - last name - invalid
A56: TC_ACF_055 | B56: =_xlfn.TEXTJOIN(CHAR(10),,Scenario!$A$25,Scenario!$C$25) -> TS016 Validate the working of 'My Account Address Book' functionality | C56: Add address - company - valid
A57: TC_ACF_056 | B57: =_xlfn.TEXTJOIN(CHAR(10),,Scenario!$A$25,Scenario!$C$25) -> TS016 Validate the working of 'My Account Address Book' functionality | C57: Add address - company - empty
A58: TC_ACF_057 | B58: =_xlfn.TEXTJOIN(CHAR(10),,Scenario!$A$25,Scenario!$C$25) -> TS016 Validate the working of 'My Account Address Book' functionality | C58: Add address - company - invalid
A59: TC_ACF_058 | B59: =_xlfn.TEXTJOIN(CHAR(10),,Scenario!$A$25,Scenario!$C$25) -> TS016 Validate the working of 'My Account Address Book' functionality | C59: Add address - address1 - valid
A60: TC_ACF_059 | B60: =_xlfn.TEXTJOIN(CHAR(10),,Scenario!$A$25,Scenario!$C$25) -> TS016 Validate the working of 'My Account Address Book' functionality | C60: Add address - address1 - invalid
A61: TC_ACF_060 | B61: =_xlfn.TEXTJOIN(CHAR(10),,Scenario!$A$25,Scenario!$C$25) -> TS016 Validate the working of 'My Account Address Book' functionality | C61: Add address - address2 - valid
... A105: TC_ACF_104 | B105: =_xlfn.TEXTJOIN(CHAR(10),,Scenario!$A$25,Scenario!$C$25) -> TS016 Validate the working of 'My Account Address Book' functionality | C105: Edit address - success
A106: TC_ACF_105 | B106: =_xlfn.TEXTJOIN(CHAR(10),,Scenario!$A$26,Scenario!$C$26) -> TS017 Validate the working of 'My Order > Order History' functionality
A107: TC_ACF_106 | B107: =_xlfn.TEXTJOIN(CHAR(10),,Scenario!$A$26,Scenario!$C$26) -> TS017 Validate the working of 'My Order > Order History' functionality
A108: TC_ACF_107 | B108: =_xlfn.TEXTJOIN(CHAR(10),,Scenario!$A$26,Scenario!$C$26) -> TS017 Validate the working of 'My Order > Order History' functionality
A109: TC_ACF_108 | B109: =_xlfn.TEXTJOIN(CHAR(10),,Scenario!$A$26,Scenario!$C$26) -> TS017 Validate the working of 'My Order > Order History' functionality
A110: TC_ACF_109 | B110: =_xlfn.TEXTJOIN(CHAR(10),,Scenario!$A$26,Scenario!$C$26) -> TS017 Validate the working of 'My Order > Order History' functionality
A111: TC_ACF_110 | B111: =_xlfn.TEXTJOIN(CHAR(10),,Scenario!$A$26,Scenario!$C$26) -> TS017 Validate the working of 'My Order > Order History' functionality
A112: TC_ACF_111 | B112: =_xlfn.TEXTJOIN(CHAR(10),,Scenario!$A$26,Scenario!$C$26) -> TS017 Validate the working of 'My Order > Order History' functionality
A113: TC_ACF_112 | B113: =_xlfn.TEXTJOIN(CHAR(10),,Scenario!$A$26,Scenario!$C$26) -> TS017 Validate the working of 'My Order > Order History' functionality
A114: TC_ACF_113 | B114: =_xlfn.TEXTJOIN(CHAR(10),,Scenario!$A$26,Scenario!$C$26) -> TS017 Validate the working of 'My Order > Order History' functionality
A115: TC_ACF_114 | B115: =_xlfn.TEXTJOIN(CHAR(10),,Scenario!$A$26,Scenario!$C$26) -> TS017 Validate the working of 'My Order > Order History' functionality
A116: TC_ACF_115 | B116: =_xlfn.TEXTJOIN(CHAR(10),,Scenario!$A$26,Scenario!$C$26) -> TS017 Validate the working of 'My Order > Order History' functionality
A117: TC_ACF_116 | B117: =_xlfn.TEXTJOIN(CHAR(10),,Scenario!$A$26,Scenario!$C$26) -> TS017 Validate the working of 'My Order > Order History' functionality
A118: TC_ACF_117 | B118: =_xlfn.TEXTJOIN(CHAR(10),,Scenario!$A$26,Scenario!$C$26) -> TS017 Validate the working of 'My Order > Order History' functionality
A119: TC_ACF_086 | B119: Validate the working of 'My Orders > Reward Points' functionality
A120: TC_ACF_087 | B120: Validate the working of 'My Orders > Returned Request' functionality
A121: TC_ACF_088 | B121: Validate the working of 'My Order > Your Transactions' functionality
A122: TC_ACF_089 | B122: Validate the working of 'My Order > Recurring Payments' functionality

Sheet Search
A1: Test Case ID | B1: Test Scenario | C1: Test Case Title | D1: Pre-requisites | E1: Test Steps | F1: Test Data | G1: Expected Result (ER) | H1: Actual Result | I1: Priority | J1: Result | K1: Comments
A2: TC_S_001 | B2: =_xlfn.TEXTJOIN(CHAR(10),,Scenario!$A$14,Scenario!$C$14) -> TS005 Validate the working of 'Search' functionality | C2: Validate search - placeholder | D2: Open application | E2: 1. Validate result (ER-1) | F2: Not applicable | G2: Search bar should have placeholder "Search"
A3: TC_S_002 | B3: =_xlfn.TEXTJOIN(CHAR(10),,Scenario!$A$14,Scenario!$C$14) -> TS005 Validate the working of 'Search' functionality | C3: Validate search - empty | D3: Open application | E3: 1. Leave input empty 2. Click search icon | F3: Not applicable | G3: Should show message "Please enter your search criteria"
A4: TC_S_003 | B4: =_xlfn.TEXTJOIN(CHAR(10),,Scenario!$A$14,Scenario!$C$14) -> TS005 Validate the working of 'Search' functionality | C4: Validate search - valid | D4: Open application | E4: 1. Input search criteria 2. Click search icon 3. Validate result (ER-1) | F4: Iphone | G4: Should show search result on current page based on search criteria
A5: TC_S_004 | B5: =_xlfn.TEXTJOIN(CHAR(10),,Scenario!$A$14,Scenario!$C$14) -> TS005 Validate the working of 'Search' functionality | C5: Validate search - exact | D5: Open application | E5: 1. Input search criteria 2. Click search icon 3. Validate result (ER-1) | F5: Apple cinima 30" | G5: Search results should at least show the exact match product
A6: TC_S_005 | B6: =_xlfn.TEXTJOIN(CHAR(10),,Scenario!$A$14,Scenario!$C$14) -> TS005 Validate the working of 'Search' functionality | C6: Validate search - partial | D6: Open application | E6: 1. Input search criteria 2. Click search icon 3. Validate result (ER-1) | F6: Apple cini | G6: Should be able to find similar item when match with partial word
A7: TC_S_006 | B7: =_xlfn.TEXTJOIN(CHAR(10),,Scenario!$A$14,Scenario!$C$14) -> TS005 Validate the working of 'Search' functionality | C7: Validate search - product name | D7: Open application | E7: 1. Input search criteria 2. Click search icon 3. Validate result (ER-1) | F7: Iphone14 | G7: Search result should be able to find item when match by product name
A8: TC_S_007 | B8: =_xlfn.TEXTJOIN(CHAR(10),,Scenario!$A$14,Scenario!$C$14) -> TS005 Validate the working of 'Search' functionality | C8: Validate search - brand name | D8: Open application | E8: 1. Input search criteria 2. Click search icon 3. Validate result (ER-1) | F8: Apple | G8: Search result should be able to find item when match by brand name
A9: TC_S_008 | B9: =_xlfn.TEXTJOIN(CHAR(10),,Scenario!$A$14,Scenario!$C$14) -> TS005 Validate the working of 'Search' functionality | C9: Validate search - product cat | D9: Open application | E9: 1. Input search criteria 2. Click search icon 3. Validate result (ER-1) | F9: Tablets | G9: Search result should be able to find item when match by product category
A10: TC_S_009 | B10: =_xlfn.TEXTJOIN(CHAR(10),,Scenario!$A$14,Scenario!$C$14) -> TS005 Validate the working of 'Search' functionality | C10: Validate search - description | D10: Open application | E10: 1. Input search criteria 2. Click search icon 3. Validate result (ER-1) | F10: 4k | G10: Search result should be able to find item when match by product description
A11: TC_S_010 | B11: =_xlfn.TEXTJOIN(CHAR(10),,Scenario!$A$14,Scenario!$C$14) -> TS005 Validate the working of 'Search' functionality | C11: Validate search - sub cat | D11: Open application | E11: 1. Input search criteria 2. Click search icon 3. Validate result (ER-1) | F11: PC | G11: Search result should be able to find item when match by product sub category
A12: TC_S_011 | B12: =_xlfn.TEXTJOIN(CHAR(10),,Scenario!$A$14,Scenario!$C$14) -> TS005 Validate the working of 'Search' functionality | C12: Validate search - availability | D12: Open application | E12: 1. Input search criteria 2. Click search icon 3. Validate result (ER-1) | F12: Available | G12: Search result should be able to find item when match by availability
A13: TC_S_012 | B13: =_xlfn.TEXTJOIN(CHAR(10),,Scenario!A14,Scenario!C14) -> TS005 Validate the working of 'Search' functionality | C13: Validate search - character boundary | D13: Open application | E13: 1. Input search criteria 2. Click search icon 3. Validate result (ER-1) | F13: accept only 2-255 characters : criteria : 4k -> result : accept criteria : 4 or any input that over 255 characters -> result : reject | G13: Search result only accept input that contain between 2 - 255 characters,If not warning message should display "Only accept 2 - 255 characters in search criteria"
A14: TC_S_013 | B14: =_xlfn.TEXTJOIN(CHAR(10),,Scenario!A14,Scenario!C14) -> TS005 Validate the working of 'Search' functionality | C14: Validate search - found | D14: Open application | E14: 1. Input search criteria 2. Click search icon 3. Validate result (ER-1) | F14: Canon EOS 5D | G14: Search result will show item in result area
A15: TC_S_014 | B15: =_xlfn.TEXTJOIN(CHAR(10),,Scenario!A14,Scenario!C14) -> TS005 Validate the working of 'Search' functionality | C15: Validate search - found multiple | D15: Open application | E15: 1. Input search criteria 2. Click search icon 3. Validate result (ER-1) | F15: Apple | G15: Search result will show item in result area
A16: TC_S_015 | B16: =_xlfn.TEXTJOIN(CHAR(10),,Scenario!A14,Scenario!C14) -> TS005 Validate the working of 'Search' functionality | C16: Validate search - not found | D16: Open application | E16: 1. Input search criteria 2. Click search icon 3. Validate result (ER-1) | F16: Hammock | G16: Search result will show message "criteria is not found"
A17: TC_S_016 | B17: =_xlfn.TEXTJOIN(CHAR(10),,Scenario!A14,Scenario!C14) -> TS005 Validate the working of 'Search' functionality | C17: Validate search - select subcat filter | D17: Open application,Search item(found) | E17: 1. Input search criteria -<refer test data - criteria> 2. Click search icon 3. Select sub category filter -<refer test data - sub category> 4. Validate result (ER-1) | F17: criteria : apple sub category : tablets | G17: Search result will only show item that match selected sub category
A18: TC_S_017 | B18: =_xlfn.TEXTJOIN(CHAR(10),,Scenario!A14,Scenario!C14) -> TS005 Validate the working of 'Search' functionality | C18: Validate list view | D18: Open application,Search item(found) | E18: 1. Click list view icon 2. Validate result (ER-1) | F18: Not applicable | G18: Search result will show item in list
A19: TC_S_018 | B19: =_xlfn.TEXTJOIN(CHAR(10),,Scenario!A14,Scenario!C14) -> TS005 Validate the working of 'Search' functionality | C19: Validate grid view | D19: Open application,Search item(found) | E19: 1. Click grid view icon 2. Validate result (ER-1) | F19: Not applicable | G19: Search result will show item in grid
A20: TC_S_019 | B20: =_xlfn.TEXTJOIN(CHAR(10),,Scenario!A14,Scenario!C14) -> TS005 Validate the working of 'Search' functionality | C20: Validate sorting | D20: Open application,Search item(found) | E20: 1. Click sort item icon 2. Select sorting type -<Refer test data> 3. Validate result (ER-1) | F20: Ascending | G20: Search result will sort by selected sorting type
A21: TC_S_020 | B21: =_xlfn.TEXTJOIN(CHAR(10),,Scenario!A14,Scenario!C14) -> TS005 Validate the working of 'Search' functionality | C21: Validate item display (quantity) | D21: Open application,Search item(found) | E21: 1. Click dropdown "show" in refine search area 2. Select quantity -<Refer test data> 3. Validate result (ER-1) | F21: 15 | G21: Search result will only show item by selected quantity per page
A22: TC_S_021 | B22: =_xlfn.TEXTJOIN(CHAR(10),,Scenario!A14,Scenario!C14) -> TS005 Validate the working of 'Search' functionality | C22: Validate item display (quantity) - over limit | D22: Open application,Search item(found), result quantity is more than selected item display | E22: 1. Click dropdown "show" in refine search area 2. Select quantity -<Refer test data> 3. Validate result (ER-1) | F22: Not applicable | G22: The exeed items will split in to page(s)
A23: TC_S_022 | B23: =_xlfn.TEXTJOIN(CHAR(10),,Scenario!A14,Scenario!C14) -> TS005 Validate the working of 'Search' functionality | C23: Validate item display (quantity) - below limit | D23: Open application,Search item(found), result quantity is less than selected item display | E23: 1. Click dropdown "show" in refine search area 2. Select quantity -<Refer test data> 3. Validate result (ER-1) | F23: Not applicable | G23: Search result will only show in one page
A24: TC_S_023 | B24: =_xlfn.TEXTJOIN(CHAR(10),,Scenario!A14,Scenario!C14) -> TS005 Validate the working of 'Search' functionality | C24: Validate navigate compare | D24: Open application,Search item(found) | E24: 1. Click compare symbol on item 2. Validate result (ER-1) | F24: Not applicable | G24: Selected item will be add to compare list

Sheet Product Comparison
A1: Test Case ID | B1: Test Scenario | C1: Test Case Title | D1: Pre-requisites | E1: Test Steps | F1: Test Data | G1: Expected Result (ER) | H1: Actual Result | I1: Priority | J1: Result | K1: Comments
A2: TC_PC_001 | B2: =_xlfn.TEXTJOIN(CHAR(10),,Scenario!A15,Scenario!C15) -> TS006 Validate the working of 'Product compare' functionality | C2: Product comparison - default | D2: Open application,enter product comparison page
A3: TC_PC_002 | B3: =_xlfn.TEXTJOIN(CHAR(10),,Scenario!A15,Scenario!C15) -> TS006 Validate the working of 'Product compare' functionality | C3: Product comparison - empty | D3: Open application,enter product comparison page
A4: TC_PC_003 | B4: =_xlfn.TEXTJOIN(CHAR(10),,Scenario!A15,Scenario!C15) -> TS006 Validate the working of 'Product compare' functionality | C4: Product comparison - limit | D4: Open application,on any product page
A5: TC_PC_004 | B5: =_xlfn.TEXTJOIN(CHAR(10),,Scenario!A15,Scenario!C15) -> TS006 Validate the working of 'Product compare' functionality | C5: Product comparison - duplicate | D5: Open application,on any product page
A6: TC_PC_005 | B6: =_xlfn.TEXTJOIN(CHAR(10),,Scenario!A15,Scenario!C15) -> TS006 Validate the working of 'Product compare' functionality | C6: Product comparison - remove | D6: Open application,enter product comparison page
A7: TC_PC_006 | B7: =_xlfn.TEXTJOIN(CHAR(10),,Scenario!A15,Scenario!C15) -> TS006 Validate the working of 'Product compare' functionality | C7: Product comparison - view detailed product | D7: Open application,enter product comparison page
A8: TC_PC_007 | B8: =_xlfn.TEXTJOIN(CHAR(10),,Scenario!A15,Scenario!C15) -> TS006 Validate the working of 'Product compare' functionality | C8: Product comparison - add item to cart | D8: Open application,enter product comparison page

Sheet HomePage
A1: Test Case ID | B1: Test Scenario | C1: Test Case Title | D1: Pre-requisites | E1: Test Steps | F1: Test Data | G1: Expected Result (ER) | H1: Actual Result | I1: Priority | J1: Result | K1: Comments
A2: TC_HP_001 | B2: =_xlfn.TEXTJOIN(CHAR(10),,Scenario!A20,Scenario!C20) -> TS011 Validate the working of 'Home page' functionality | C2: Validate top menu | D2: Open https://demo.opencart.com | E2: 1. Validate that top menu is displayed correctly (Validate ER-1) | F2: No Applicable | G2: 1) Top menu should displayed at top of the page under header which contain top parent categories of products as following : Desktops Laptop & Notebooks Components Tablets Software Phone & PDAs Cameras MP3 Players
A3: TC_HP_002 | B3: =_xlfn.TEXTJOIN(CHAR(10),,Scenario!A20,Scenario!C20) -> TS011 Validate the working of 'Home page' functionality | C3: Validate 'Direct back to home page' from product page | D3: Open https://demo.opencart.com | E3: 1. Click on product from 'Featured products - <Refer Test Data> 2. Wait for application to redirect user to product page (Validate ER-1) 3. Click store logo at top right corner on header (Validate ER-2) | F3: MacBook | G3: 1) User should redirect to product page 2) User should redirect back to home page
A4: TC_HP_003 | B4: =_xlfn.TEXTJOIN(CHAR(10),,Scenario!A20,Scenario!C20) -> TS011 Validate the working of 'Home page' functionality | C4: Validate 'Direct back to home page' from shopping cart page | D4: Open https://demo.opencart.com | E4: 1. Click 'Shopping Cart' (Validate ER-1) 2. Click store logo at top right corner on header (Validate ER-2) | F4: No Applicable | G4: 1) User should redirect to shopping cart page 2) User should redirect back to home page
A5: TC_HP_004 | B5: =_xlfn.TEXTJOIN(CHAR(10),,Scenario!A20,Scenario!C20) -> TS011 Validate the working of 'Home page' functionality | C5: Slideshow display image | D5: Open https://demo.opencart.com | E5: 1. Validate display image (Validate ER-1) | F5: No Applicable | G5: 1) All Selected images will appear in slideshow
A6: TC_HP_005 | B6: =_xlfn.TEXTJOIN(CHAR(10),,Scenario!A20,Scenario!C20) -> TS011 Validate the working of 'Home page' functionality | C6: Slideshow automatically change image | D6: Open https://demo.opencart.com | E6: 1. Wait a certain amount of time (Validate ER-1) | F6: No Applicable | G6: 1) image in slidesohw should shift to the next one
A7: TC_HP_006 | B7: =_xlfn.TEXTJOIN(CHAR(10),,Scenario!A20,Scenario!C20) -> TS011 Validate the working of 'Home page' functionality | C7: Slideshow manually change image | D7: Open https://demo.opencart.com | E7: 1. Validate display image (Validate ER-1) 2. Select another dot under image (Validate ER-2) | F7: No Applicable | G7: 1) image should display correctly 2) image should shift to the selected one
A8: TC_HP_007 | B8: =_xlfn.TEXTJOIN(CHAR(10),,Scenario!A20,Scenario!C20) -> TS011 Validate the working of 'Home page' functionality | C8: Slideshow select product | D8: Open https://demo.opencart.com | E8: 1. Click display image - <Refer Test Data> 2. Validate navigation result (Validate ER-1) | F8: Slideshow image : 'MacBook' | G8: 1) User should redirect to product page of selected product
A9: TC_HP_008 | B9: =_xlfn.TEXTJOIN(CHAR(10),,Scenario!A20,Scenario!C20) -> TS011 Validate the working of 'Home page' functionality | C9: Validate 'Featured products' details | D9: Open https://demo.opencart.com | E9: 1. Validate featured product display correctly (Validate ER-1) | F9: No Applicable | G9: 1) Featured product should display under slideshow contain following elements: 1. Item Box 2. Product image 3. Product name 4. Product price 5. 'ADD TO CART' button 6. 'Wish list' button 7. 'Compare product' button
A10: TC_HP_009 | B10: =_xlfn.TEXTJOIN(CHAR(10),,Scenario!A20,Scenario!C20) -> TS011 Validate the working of 'Home page' functionality | C10: Validate 'Featured products' swish list of product | D10: Open https://demo.opencart.com | E10: 1. Click another dot under displayed featured (Validate ER-1) | F10: No Applicable | G10: 1) Featured product should shift to another set of displayed product
A11: TC_HP_010 | B11: =_xlfn.TEXTJOIN(CHAR(10),,Scenario!A20,Scenario!C20) -> TS011 Validate the working of 'Home page' functionality | C11: Select product from 'Featured products' | D11: Open https://demo.opencart.com | E11: 1. Click on product image from 'Featured' - <Refer Test Data> 2. Validate nagivation result (Validate ER-1) | F11: Product : MacBook | G11: 1) User should redirect to product page of selected product
A12: TC_HP_011 | B12: =_xlfn.TEXTJOIN(CHAR(10),,Scenario!A20,Scenario!C20) -> TS011 Validate the working of 'Home page' functionality | C12: Validate footer | D12: Open https://demo.opencart.com | E12: 1. Validate that footer is displayed correctly (Validate ER-1) | F12: No Applicable | G12: 1) Footer should displayed at bottom of the page and divided into following section : Information : About Us, Delivery Information, Privacy Policy, Term & Conditions Customer Services : Contact Us, Returns, Site Map Extra : Brands, Gift Voucher, Affiliate, Specials My Account : My Account, Order History, Wish List, Newsletter

Sheet Top Menu
A1: Test Case ID | B1: Test Scenario | C1: Test Case Title | D1: Pre-requisites | E1: Test Steps | F1: Test Data | G1: Expected Result (ER) | H1: Actual Result | I1: Priority | J1: Result | K1: Comments
A2: TC_TM_01 | B2: =_xlfn.TEXTJOIN(CHAR(10),,Scenario!A40,Scenario!C40) -> TS031 Validate the working of 'Top Menu' options' functionality | C2: Validate top menu visibility on any page | D2: Open https://demo.opencart.com or currently in any page on application | E2: 1. Validate that top menu is displayed correctly ( Validate ER-1) | F2: No Applicable | G2: Top menu should be displayed at top of the page on every page of the store
A3: TC_TM_02 | B3: =_xlfn.TEXTJOIN(CHAR(10),,Scenario!A40,Scenario!C40) -> TS031 Validate the working of 'Top Menu' options' functionality | C3: Validate top menu content | D3: Open https://demo.opencart.com | E3: 1. Validate top menu contents display correctly (Validate ER-1) | F3: No Applicable | G3: Top menu should contain parent categories as following : - Desktops - Laptops & Notebooks - Components - Tablets - Software - Phones & PDAs - Cameras - MP3 Players
A4: TC_TM_03 | B4: =_xlfn.TEXTJOIN(CHAR(10),,Scenario!A40,Scenario!C40) -> TS031 Validate the working of 'Top Menu' options' functionality | C4: Validate top menu action 'click' on parent category | D4: Open https://demo.opencart.com | E4: 1. Click on any of 'top menu' content - <Refer Test Data> 2. Validate result ( Validate ER-1) | F4: Desktops | G4: Should navigate user to selected category page
A5: TC_TM_04 | B5: =_xlfn.TEXTJOIN(CHAR(10),,Scenario!A40,Scenario!C40) -> TS031 Validate the working of 'Top Menu' options' functionality | C5: Validate top menu action 'hover' | D5: Open https://demo.opencart.com | E5: 1. Hover on any of 'top menu' content - <Refer Test Data> 2. Validate result (Validate ER-1) | F5: Laptops & Notebooks | G5: A drop-down menu will display the sub-categories for that parent category
A6: TC_TM_05 | B6: =_xlfn.TEXTJOIN(CHAR(10),,Scenario!A40,Scenario!C40) -> TS031 Validate the working of 'Top Menu' options' functionality | C6: Validate top menu action 'click' on sub-category | D6: Open https://demo.opencart.com | E6: 1. Hover on 'top menu' content - <Refer Test Data - Parent Category> 2. Click on 'sub category' - <Refer Test Data - Subcategory> 3. Validate result (Validate ER-1) | F6: Parent Category : Desktops Subcategory : CPU | G6: Should navigate user to product page which display only selected subcategory

Sheet Header
A1: Test Case ID | B1: Test Scenario | C1: Test Case Title | D1: Pre-requisites | E1: Test Steps | F1: Test Data | G1: Expected Result (ER) | H1: Actual Result | I1: Priority | J1: Result | K1: Comments
A2: TC_HD_001 | B2: =_xlfn.TEXTJOIN(CHAR(10),,Scenario!$A$39,Scenario!$C$39) -> TS030 Validate the working of 'Header' options' functionality | C2: Validate header | D2: Open https://demo.opencart.com Navigate in any page of application | E2: 1. Validate that header is displayed correctly (Validate ER-1) | F2: No Applicable | G2: Header should displayed at top of the page and contain following options Store logo Currency block Shopping Cart Search box Links Telephone My Account
A3: TC_HD_002 | B3: =_xlfn.TEXTJOIN(CHAR(10),,Scenario!$A$39,Scenario!$C$39) -> TS030 Validate the working of 'Header' options' functionality | C3: Validate store logo funtionality | D3: Open https://demo.opencart.com Navigate in any page of application | E3: 1. Click store logo (Validate ER-1) | F3: No Applicable | G3: Should navigate to home page
A4: TC_HD_003 | B4: =_xlfn.TEXTJOIN(CHAR(10),,Scenario!$A$39,Scenario!$C$39) -> TS030 Validate the working of 'Header' options' functionality | C4: Validate currency functionality | D4: Open https://demo.opencart.com | E4: 1. Click at 'Currency' on the left side of header (Validate ER-1) | F4: No Applicable | G4: Correct 2 available option should be USD($) and EUR(€)
A5: TC_HD_004 | B5: =_xlfn.TEXTJOIN(CHAR(10),,Scenario!$A$39,Scenario!$C$39) -> TS030 Validate the working of 'Header' options' functionality | C5: Validate telephone display | D5: Open https://demo.opencart.com | E5: 1. Validate company telephone number (Validate ER-1) | F5: No Applicable | G5: Company telephone number should be '123456789'
A6: TC_HD_005 | B6: =_xlfn.TEXTJOIN(CHAR(10),,Scenario!$A$39,Scenario!$C$39) -> TS030 Validate the working of 'Header' options' functionality | C6: Validate 'My Account' link | D6: Open https://demo.opencart.com | E6: 1. Click 'My Account' link (Validate ER-1) | F6: No Applicable | G6: Should display dropdown list 'login' and 'register'
A7: TC_HD_006 | B7: =_xlfn.TEXTJOIN(CHAR(10),,Scenario!$A$39,Scenario!$C$39) -> TS030 Validate the working of 'Header' options' functionality | C7: Validate link 'My Account' - 'Register' | D7: Open https://demo.opencart.com | E7: 1. Click 'My Account' link (Validate ER-1) | F7: No Applicable | G7: Should redirect to register page
A8: TC_HD_007 | B8: =_xlfn.TEXTJOIN(CHAR(10),,Scenario!$A$39,Scenario!$C$39) -> TS030 Validate the working of 'Header' options' functionality | C8: Validate link 'My Account' - 'Login' | D8: Open https://demo.opencart.com | E8: 1. Click 'My Account' link (Validate ER-1) | F8: No Applicable | G8: Should redirect to login page
A9: TC_HD_008 | B9: =_xlfn.TEXTJOIN(CHAR(10),,Scenario!$A$39,Scenario!$C$39) -> TS030 Validate the working of 'Header' options' functionality | C9: Validate 'My Account' link after logged in | D9: Open https://demo.opencart.com, logged in | E9: 1. Click 'My Account' link (Validate ER-1) | F9: No Applicable | G9: Should have option : my account, order history, transactions, download, logout
A10: TC_HD_009 | B10: =_xlfn.TEXTJOIN(CHAR(10),,Scenario!$A$39,Scenario!$C$39) -> TS030 Validate the working of 'Header' options' functionality | C10: Validate 'My Account' - my account | D10: Open https://demo.opencart.com, logged in | E10: 1. Click 'My Account' link (Validate ER-1) 2. Click 'My Account' link from list (Validate ER-2) | F10: No Applicable | G10: Should navigate user to my account page
A11: TC_HD_010 | B11: =_xlfn.TEXTJOIN(CHAR(10),,Scenario!$A$39,Scenario!$C$39) -> TS030 Validate the working of 'Header' options' functionality | C11: Validate 'My Account' - order history | D11: Open https://demo.opencart.com, logged in | E11: 1. Click 'My Account' link (Validate ER-1) 2. Click 'Order history' link from list (Validate ER-2) | F11: No Applicable | G11: Should navigate user to history page
A12: TC_HD_011 | B12: =_xlfn.TEXTJOIN(CHAR(10),,Scenario!$A$39,Scenario!$C$39) -> TS030 Validate the working of 'Header' options' functionality | C12: Validate 'My Account' - transaction | D12: Open https://demo.opencart.com, logged in | E12: 1. Click 'My Account' link (Validate ER-1) 2. Click 'Transaction' link from list (Validate ER-2) | F12: No Applicable | G12: Should navigate user to transaction page
A13: TC_HD_012 | B13: =_xlfn.TEXTJOIN(CHAR(10),,Scenario!$A$39,Scenario!$C$39) -> TS030 Validate the working of 'Header' options' functionality | C13: Validate 'My Account' - download | D13: Open https://demo.opencart.com, logged in | E13: 1. Click 'My Account' link (Validate ER-1) 2. Click 'Download' link from list (Validate ER-2) | F13: No Applicable | G13: Should navigate user to download page
... A24: TC_HD_023 | B24: =_xlfn.TEXTJOIN(CHAR(10),,Scenario!$A$39,Scenario!$C$39) -> TS030 Validate the working of 'Header' options' functionality | C24: Validate search box | D24: Open https://demo.opencart.com | E24: 1. Input text into search box - <Refer Test Data> 2. Click Search button (Validate ER-1) | F24: "Iphone" | G24: Should redirect to search result page
A25: TC_HD_024 | B25: =_xlfn.TEXTJOIN(CHAR(10),,Scenario!$A$39,Scenario!$C$39) -> TS030 Validate the working of 'Header' options' functionality | C25: Validate search box - too many characters | D25: Open https://demo.opencart.com | E25: 1. Input text into search box - <Refer Test Data> 2. Click Search button (Validate ER-1) | F25: a text that has over a 500 characters | G25: Should show error message "your input is over the character limit" | H25: do not show error message and proceed with data. sometimes cause error 522 | J25: Defect-003
A26: TC_HD_025 | B26: =_xlfn.TEXTJOIN(CHAR(10),,Scenario!$A$39,Scenario!$C$39) -> TS030 Validate the working of 'Header' options' functionality | C26: Validate location show correctly | D26: Open https://demo.opencart.com,navigate through any page of the application | E26: 1. Validate result (Validate ER-1) | F26: No Applicable | G26: Should show correct location of the current page
A27: TC_HD_026 | B27: =_xlfn.TEXTJOIN(CHAR(10),,Scenario!$A$39,Scenario!$C$39) -> TS030 Validate the working of 'Header' options' functionality | C27: Validate quick access for location | D27: Open https://demo.opencart.com,navigate through any page of the application except home page | E27: 1. Select one of any previous page on location - <Refer test data : target> 2. Validate result (Validate ER-1) | F27: location : home > account > password target : account | G27: Should navigate user to account page

Sheet Footer
A1: Test Case ID | B1: Test Scenario | C1: Test Case Title | D1: Pre-requisites | E1: Test Steps | F1: Test Data | G1: Expected Result (ER) | H1: Actual Result | I1: Priority | J1: Result | K1: Comments
A2: TC_FT_001 | B2: =_xlfn.TEXTJOIN(CHAR(10),,Scenario!A41,Scenario!C41) -> TS032 Validate the working of 'Footer' options' functionality | C2: Validate footer contents | D2: Open application | E2: 1. Validate content of footer (Validate ER-1) | F2: No Applicable | G2: Footer should located at bottom of every page and contain following contents : Information which have : About Us, Delivery Information, Privacy Policy, Terms & Conditions Customer Service which have: Contact Us, Returns, Site Map Extras which have: Brands, Gift Vouchers, Affiliates, Specials My Account which have: My Account, Order History, Wish List, Newsletter
A3: TC_FT_002 | B3: =_xlfn.TEXTJOIN(CHAR(10),,Scenario!A41,Scenario!C41) -> TS032 Validate the working of 'Footer' options' functionality | C3: Validate footer link 'About Us' | D3: Open application | E3: 1. Click on footer content - <Refer Test Data> 2. Validate navigation result (Validate ER-1) | F3: =SUBSTITUTE(MID(C3,22,30),"'","") -> About Us | G3: ="Should navigate user to "&MID(C3,22,30)&". A proper text/information should display on this page" -> Should navigate user to 'About Us'. A proper text/information should display on this page
A4: TC_FT_003 | B4: =_xlfn.TEXTJOIN(CHAR(10),,Scenario!A41,Scenario!C41) -> TS032 Validate the working of 'Footer' options' functionality | C4: Validate footer link 'Delivery Information' | D4: Open application | E4: 1. Click on footer content - <Refer Test Data> 2. Validate navigation result (Validate ER-1) | F4: =SUBSTITUTE(MID(C4,22,30),"'","") -> Delivery Information | G4: ="Should navigate user to "&MID(C4,22,30)&". A proper text/information should display on this page" -> Should navigate user to 'Delivery Information'. A proper text/information should display on this page
A5: TC_FT_004 | B5: =_xlfn.TEXTJOIN(CHAR(10),,Scenario!A41,Scenario!C41) -> TS032 Validate the working of 'Footer' options' functionality | C5: Validate fotter link 'Privacy Policy' | D5: Open application | E5: 1. Click on footer content - <Refer Test Data> 2. Validate navigation result (Validate ER-1) | F5: =SUBSTITUTE(MID(C5,22,30),"'","") -> Privacy Policy | G5: ="Should navigate user to "&MID(C5,22,30)&". A proper text/information should display on this page" -> Should navigate user to 'Privacy Policy'. A proper text/information should display on this page
A6: TC_FT_005 | B6: =_xlfn.TEXTJOIN(CHAR(10),,Scenario!A41,Scenario!C41) -> TS032 Validate the working of 'Footer' options' functionality | C6: Validate footer link 'Term & Conditions' | D6: Open application | E6: 1. Click on footer content - <Refer Test Data> 2. Validate navigation result (Validate ER-1) | F6: =SUBSTITUTE(MID(C6,22,30),"'","") -> Term & Conditions | G6: ="Should navigate user to "&MID(C6,22,30)&". A proper text/information should display on this page" -> Should navigate user to 'Term & Conditions'. A proper text/information should display on this page
A7: TC_FT_006 | B7: =_xlfn.TEXTJOIN(CHAR(10),,Scenario!A41,Scenario!C41) -> TS032 Validate the working of 'Footer' options' functionality | C7: Validate footer link 'Contact Us' | D7: Open application | E7: 1. Click on footer content - <Refer Test Data> 2. Validate navigation result (Validate ER-1) | F7: =SUBSTITUTE(MID(C7,22,30),"'","") -> Contact Us | G7: ="Should navigate user to "&MID(C7,22,30)&". A proper text/information should display on this page" -> Should navigate user to 'Contact Us'. A proper text/information should display on this page
A8: TC_FT_007 | B8: =_xlfn.TEXTJOIN(CHAR(10),,Scenario!A41,Scenario!C41) -> TS032 Validate the working of 'Footer' options' functionality | C8: Validate footer link ' Returns' | D8: Open application | E8: 1. Click on footer content - <Refer Test Data> 2. Validate navigation result (Validate ER-1) | F8: =SUBSTITUTE(MID(C8,22,30),"'","") -> Returns | G8: ="Should navigate user to "&MID(C8,22,30)&". A proper text/information should display on this page" -> Should navigate user to ' Returns'. A proper text/information should display on this page
A9: TC_FT_008 | B9: =_xlfn.TEXTJOIN(CHAR(10),,Scenario!A41,Scenario!C41) -> TS032 Validate the working of 'Footer' options' functionality | C9: Validate footer link 'Site Map' | D9: Open application | E9: 1. Click on footer content - <Refer Test Data> 2. Validate navigation result (Validate ER-1) | F9: =SUBSTITUTE(MID(C9,22,30),"'","") -> Site Map | G9: ="Should navigate user to "&MID(C9,22,30)&". A proper text/information should display on this page" -> Should navigate user to 'Site Map'. A proper text/information should display on this page
A10: TC_FT_009 | B10: =_xlfn.TEXTJOIN(CHAR(10),,Scenario!A41,Scenario!C41) -> TS032 Validate the working of 'Footer' options' functionality | C10: Validate footer link 'Brands' | D10: Open application | E10: 1. Click on footer content - <Refer Test Data> 2. Validate navigation result (Validate ER-1) | F10: =SUBSTITUTE(MID(C10,22,30),"'","") -> Brands | G10: ="Should navigate user to "&MID(C10,22,30)&". A proper text/information should display on this page" -> Should navigate user to 'Brands'. A proper text/information should display on this page
A11: TC_FT_010 | B11: =_xlfn.TEXTJOIN(CHAR(10),,Scenario!A41,Scenario!C41) -> TS032 Validate the working of 'Footer' options' functionality | C11: Validate footer link 'Gift Voucher' | D11: Open application | E11: 1. Click on footer content - <Refer Test Data> 2. Validate navigation result (Validate ER-1) | F11: =SUBSTITUTE(MID(C11,22,30),"'","") -> Gift Voucher | G11: ="Should navigate user to "&MID(C11,22,30)&". A proper text/information should display on this page" -> Should navigate user to 'Gift Voucher'. A proper text/information should display on this page
A12: TC_FT_011 | B12: =_xlfn.TEXTJOIN(CHAR(10),,Scenario!A41,Scenario!C41) -> TS032 Validate the working of 'Footer' options' functionality | C12: Validate footer link 'Affiliates' | D12: Open application | E12: 1. Click on footer content - <Refer Test Data> 2. Validate navigation result (Validate ER-1) | F12: =SUBSTITUTE(MID(C12,22,30),"'","") -> Affiliates | G12: ="Should navigate user to "&MID(C12,22,30)&". A proper text/information should display on this page" -> Should navigate user to 'Affiliates'. A proper text/information should display on this page
A13: TC_FT_012 | B13: =_xlfn.TEXTJOIN(CHAR(10),,Scenario!A41,Scenario!C41) -> TS032 Validate the working of 'Footer' options' functionality | C13: Validate footer link 'Specials' | D13: Open application | E13: 1. Click on footer content - <Refer Test Data> 2. Validate navigation result (Validate ER-1) | F13: =SUBSTITUTE(MID(C13,22,30),"'","") -> Specials | G13: ="Should navigate user to "&MID(C13,22,30)&". A proper text/information should display on this page" -> Should navigate user to 'Specials'. A proper text/information should display on this page
A14: TC_FT_013 | B14: =_xlfn.TEXTJOIN(CHAR(10),,Scenario!A41,Scenario!C41) -> TS032 Validate the working of 'Footer' options' functionality | C14: Validate footer link 'My Account' | D14: Open application | E14: 1. Click on footer content - <Refer Test Data> 2. Validate navigation result (Validate ER-1) | F14: =SUBSTITUTE(MID(C14,22,30),"'","") -> My Account | G14: ="Should navigate user to "&MID(C14,22,30)&". A proper text/information should display on this page" -> Should navigate user to 'My Account'. A proper text/information should display on this page
A15: TC_FT_014 | B15: =_xlfn.TEXTJOIN(CHAR(10),,Scenario!A41,Scenario!C41) -> TS032 Validate the working of 'Footer' options' functionality | C15: Validate footer link 'Order History' | D15: Open application | E15: 1. Click on footer content - <Refer Test Data> 2. Validate navigation result (Validate ER-1) | F15: =SUBSTITUTE(MID(C15,22,30),"'","") -> Order History | G15: ="Should navigate user to "&MID(C15,22,30)&". A proper text/information should display on this page" -> Should navigate user to 'Order History'. A proper text/information should display on this page
A16: TC_FT_015 | B16: =_xlfn.TEXTJOIN(CHAR(10),,Scenario!A41,Scenario!C41) -> TS032 Validate the working of 'Footer' options' functionality | C16: Validate footer link 'Wish List' | D16: Open application | E16: 1. Click on footer content - <Refer Test Data> 2. Validate navigation result (Validate ER-1) | F16: =SUBSTITUTE(MID(C16,22,30),"'","") -> Wish List | G16: ="Should navigate user to "&MID(C16,22,30)&". A proper text/information should display on this page" -> Should navigate user to 'Wish List'. A proper text/information should display on this page
A17: TC_FT_016 | B17: =_xlfn.TEXTJOIN(CHAR(10),,Scenario!A41,Scenario!C41) -> TS032 Validate the working of 'Footer' options' functionality | C17: Validate footer link 'Newletter' | D17: Open application | E17: 1. Click on footer content - <Refer Test Data> 2. Validate navigation result (Validate ER-1) | F17: =SUBSTITUTE(MID(C17,22,30),"'","") -> Newletter | G17: ="Should navigate user to "&MID(C17,22,30)&". A proper text/information should display on this page" -> Should navigate user to 'Newletter'. A proper text/information should display on this page

Sheet Product Pages
A1: Test Case ID | B1: Test Scenario | C1: Test Case Title | D1: Pre-requisites | E1: Test Steps | F1: Test Data | G1: Expected Result (ER) | H1: Actual Result | I1: Priority | J1: Result | K1: Comments
A2: TC_PP_001 | B2: =_xlfn.TEXTJOIN(CHAR(10),,Scenario!A16,Scenario!C16) -> TS007 Validate the working of 'Product page' functionality | C2: Validate product page contain a complete elements | D2: Open application, Open product page | E2: 1. Validate product page element (Validate ER-1) | F2: Not applicable | G2: Product page should contain following sections : Product image, Product details, Cart, Rating/Sharing, Description tab, Review tab
A3: TC_PP_002 | B3: =_xlfn.TEXTJOIN(CHAR(10),,Scenario!A16,Scenario!C16) -> TS007 Validate the working of 'Product page' functionality | C3: Validate product images displayed correctly | D3: Open application, Open product page | E3: 1. Validate product page image (Validate ER-1) | F3: Not applicable | G3: Product image can be displayed under title on the left-side, along with alternate views of the product underneath it in smaller box
A4: TC_PP_003 | B4: =_xlfn.TEXTJOIN(CHAR(10),,Scenario!A16,Scenario!C16) -> TS007 Validate the working of 'Product page' functionality | C4: Validate product images expand functionality | D4: Open application, Open product page | E4: 1. Click on main image 2. Validate expand function (Validate ER-1) | F4: Not applicable | G4: Product image should expand within the window
A5: TC_PP_004 | B5: =_xlfn.TEXTJOIN(CHAR(10),,Scenario!A16,Scenario!C16) -> TS007 Validate the working of 'Product page' functionality | C5: Validate product details information | D5: Open application, Open product page | E5: 1. Validate product details ( Validate ER-1) | F5: Not applicable | G5: Product details should contain : The product code, availability, price and displayed correctly
A6: TC_PP_005 | B6: =_xlfn.TEXTJOIN(CHAR(10),,Scenario!A16,Scenario!C16) -> TS007 Validate the working of 'Product page' functionality | C6: Validate accept product quantity | D6: Open application, Open product page | E6: 1. Input test data into quantity box - <Refer test data> 2. Click 'Add to Cart' button 3. Validate product details (Validate ER-1) | F6: Quantity : 5 | G6: Product added to cart successfully
A7: TC_PP_006 | B7: =_xlfn.TEXTJOIN(CHAR(10),,Scenario!A16,Scenario!C16) -> TS007 Validate the working of 'Product page' functionality | C7: Validate reject product quantity | D7: Open application, Open product page | E7: 1. Input test data into quantity box - <Refer test data> 2. Click 'Add to Cart' button 3. Validate product details (Validate ER-1) | F7: Quantity : -5 Quantity : two | G7: Error message should appear "Please input quantity correctly"
A8: TC_PP_007 | B8: =_xlfn.TEXTJOIN(CHAR(10),,Scenario!A16,Scenario!C16) -> TS007 Validate the working of 'Product page' functionality | C8: Validate availability of product | D8: Open application, Open product page, Product is available | E8: 1. Validate product availability (Validate ER-1) | F8: Not applicable | G8: Product detail availability should be : 'In Stock' and 'Add to Cart' button should be enabled
A9: TC_PP_008 | B9: =_xlfn.TEXTJOIN(CHAR(10),,Scenario!A16,Scenario!C16) -> TS007 Validate the working of 'Product page' functionality | C9: Validate unavailability of product | D9: Open application, Open product page, Product is out of stock | E9: 1. Validate product availability (Validate ER-1) | F9: Not applicable | G9: Product detail availability should be : 'Out of Stock' and 'Add to Cart' button should be disabled
A10: TC_PP_009 | B10: =_xlfn.TEXTJOIN(CHAR(10),,Scenario!A16,Scenario!C16) -> TS007 Validate the working of 'Product page' functionality | C10: Validate wish list funtionality | D10: Open application, Open product page | E10: 1. Click on 'wish list' button above the product name(Hearth Symbol) 2. Validate the result (Validate ER-1) | F10: Not applicable | G10: Page should display "Wish list added successfully"
A11: TC_PP_010 | B11: =_xlfn.TEXTJOIN(CHAR(10),,Scenario!A16,Scenario!C16) -> TS007 Validate the working of 'Product page' functionality | C11: Validate compare funtionality | D11: Open application, Open product page | E11: 1. Click on 'compare' button above the product name(next to 'wish list' button) 2. Validate the result (Validate ER-1) | F11: Not applicable | G11: Product should added to compare list
A12: TC_PP_011 | B12: =_xlfn.TEXTJOIN(CHAR(10),,Scenario!A16,Scenario!C16) -> TS007 Validate the working of 'Product page' functionality | C12: Validate rating functionality | D12: Open application, Open product page | E12: 1. Click on the star underneath 'Add to Cart' button 2. Validate the result (Validate ER-1) | F12: Not applicable | G12: The star should change based on average of total star
A13: TC_PP_012 | B13: =_xlfn.TEXTJOIN(CHAR(10),,Scenario!A16,Scenario!C16) -> TS007 Validate the working of 'Product page' functionality | C13: Validate sharing funtionality | D13: Open application, Open product page | E13: 1. Click on social media button 2. Validate the result (Validate ER-1) | F13: Not applicable | G13: Should open new window that connect to selected platform
A14: TC_PP_013 | B14: =_xlfn.TEXTJOIN(CHAR(10),,Scenario!A16,Scenario!C16) -> TS007 Validate the working of 'Product page' functionality | C14: Validate description tab display correctly | D14: Open application, Open product page | E14: 1. Validate product description ( Validate ER-1) | F14: Not applicable | G14: Detailed description of the product should display correctly
A15: TC_PP_014 | B15: =_xlfn.TEXTJOIN(CHAR(10),,Scenario!A16,Scenario!C16) -> TS007 Validate the working of 'Product page' functionality | C15: Validate review functionality | D15: Open application, Open product page | E15: 1. Click on 'write a review' link underneath 'Add to Cart' button 2. Write review(s) - <Refer test data> 3. Click send (Validate ER-1) | F15: This product is over heat easily' | G15: Should display message 'Review succesful thank you for your review'
A16: TC_PP_015 | B16: =_xlfn.TEXTJOIN(CHAR(10),,Scenario!A16,Scenario!C16) -> TS007 Validate the working of 'Product page' functionality | C16: Validate review functionality - error | D16: Open application, Open product page | E16: 1. Click on 'write a review' link underneath 'Add to Cart' button 2. Do not input any text in review 3. Click send (Validate ER-1) | F16: Not applicable | G16: Should display a required fied or 'please write a review' message
A17: TC_PP_016 | B17: =_xlfn.TEXTJOIN(CHAR(10),,Scenario!A16,Scenario!C16) -> TS007 Validate the working of 'Product page' functionality | C17: Validate category listing product | D17: Open application, Select Category from 'top menu' | E17: 1. Validate category page(Validate ER-1) | F17: Not applicable | G17: Should display selection of products based on category
A18: TC_PP_017 | B18: =_xlfn.TEXTJOIN(CHAR(10),,Scenario!A16,Scenario!C16) -> TS007 Validate the working of 'Product page' functionality | C18: Validate category listing product - 'Category' | D18: Open application, Select Category from 'top menu' | E18: 1. Validate category page displayed corectly (Validate ER-1) | F18: Not applicable | G18: Should display the following elements : Parent category tab on the left side of the screen that list sub-category underneath
A19: TC_PP_018 | B19: =_xlfn.TEXTJOIN(CHAR(10),,Scenario!A16,Scenario!C16) -> TS007 Validate the working of 'Product page' functionality | C19: Validate sub-category functionality | D19: Open application, Select Category from 'top menu' | E19: 1. Click on selected sub-category - <Refer test data> 2. Validate result (Validate ER-1) | F19: Sub categoty : Mac | G19: Product list should change based on selected sub-category
A20: TC_PP_019 | B20: =_xlfn.TEXTJOIN(CHAR(10),,Scenario!A16,Scenario!C16) -> TS007 Validate the working of 'Product page' functionality | C20: Validate sub-category functionality - empty | D20: Open application, Select Category from 'top menu' | E20: 1. Click on selected sub-category - <Refer test data> 2. Validate result (Validate ER-1) | F20: Sub categoty : Software | G20: Product list should display message 'There is no product in this section'
A21: TC_PP_020 | B21: =_xlfn.TEXTJOIN(CHAR(10),,Scenario!A16,Scenario!C16) -> TS007 Validate the working of 'Product page' functionality | C21: Validate displayed preference - listing type option | D21: Open application, Select Category from 'top menu' | E21: 1. Validate result (Validate ER-1) | F21: Not applicable | G21: there are 2 type avialable by 'list' or 'grid'
A22: TC_PP_021 | B22: =_xlfn.TEXTJOIN(CHAR(10),,Scenario!A16,Scenario!C16) -> TS007 Validate the working of 'Product page' functionality | C22: Validate displayed preference - listing type selection | D22: Open application, Select Category from 'top menu' | E22: 1. Select display type - <Refer test data> 2. Validate result (Validate ER-1) | F22: display type : list | G22: Product list should change displayed type to list
A23: TC_PP_022 | B23: =_xlfn.TEXTJOIN(CHAR(10),,Scenario!A16,Scenario!C16) -> TS007 Validate the working of 'Product page' functionality | C23: Validate displayed preference - sorting option | D23: Open application, Select Category from 'top menu' | E23: 1. Click on sorting dropdown box 2. Validate result (Validate ER-1) | F23: Not applicable | G23: there are option for sorting as following : by name, price, rating, model
A24: TC_PP_023 | B24: =_xlfn.TEXTJOIN(CHAR(10),,Scenario!A16,Scenario!C16) -> TS007 Validate the working of 'Product page' functionality | C24: Validate displayed preference - sorting selection | D24: Open application, Select Category from 'top menu' | E24: 1. Click on sorting dropdown box 2. Select sorting type - <Refer test data> 3. Validate result (Validate ER-1) | F24: Sorting by : Price | G24: Product list should displayed and ordering by price
A25: TC_PP_024 | B25: =_xlfn.TEXTJOIN(CHAR(10),,Scenario!A16,Scenario!C16) -> TS007 Validate the working of 'Product page' functionality | C25: Validate displayed preference - displaying number | D25: Open application, Select Category from 'top menu' | E25: 1. Click on show dropdown box 2. Validate result (Validate ER-1) | F25: Not applicable | G25: Amount of product displayed can change from 15 up to 100
A26: TC_PP_025 | B26: =_xlfn.TEXTJOIN(CHAR(10),,Scenario!A16,Scenario!C16) -> TS007 Validate the working of 'Product page' functionality | C26: Validate displayed preference - displaying number selection | D26: Open application, Select Category from 'top menu' | E26: 1. Click on show dropdown box 2. Select amount for displaying the product - <Refer test data> 3. Validate result (Validate ER-1) | F26: Amount : 15 | G26: Amount of product displayed should be maximum at 15
A27: TC_PP_026 | B27: =_xlfn.TEXTJOIN(CHAR(10),,Scenario!A16,Scenario!C16) -> TS007 Validate the working of 'Product page' functionality | C27: Validate displayed preference - displaying number selection product not enough | D27: Open application, Select Category from 'top menu' | E27: 1. Click on show dropdown box 2. Select amount for displaying the product - <Refer test data> 3. Validate result (Validate ER-1) | F27: Amount : 100 | G27: The remaining amount should not shown at all
A28: TC_PP_027 | B28: =_xlfn.TEXTJOIN(CHAR(10),,Scenario!A16,Scenario!C16) -> TS007 Validate the working of 'Product page' functionality | C28: Validate access to product comparison page | D28: Open application, Open product page | E28: 1. Add product to compare list by click 'Compare this product' button - <Refer test data> 2. Click 'Product Compare' button on top left side of product list 3. Validate result (Validate ER-1) | F28: Product : iMac & MacBook | G28: Should navigate user to product comparison page
A29: TC_PP_028 | B29: =_xlfn.TEXTJOIN(CHAR(10),,Scenario!A16,Scenario!C16) -> TS007 Validate the working of 'Product page' functionality | C29: Validate product comparison page elements | D29: Open application,Open compare product page | E29: 1. Validate result (Validate ER-1) | F29: Not applicable | G29: The product comparison page should displayed 2 or more product compare to each other. the specifications that has to compare will contain these following: product name, product image, price, features(show differently depend on product type) with a button to add product to cart or remove from compare list
A30: TC_PP_029 | B30: =_xlfn.TEXTJOIN(CHAR(10),,Scenario!A16,Scenario!C16) -> TS007 Validate the working of 'Product page' functionality | C30: Validate product comparison add product to cart | D30: Open application,Open compare product page | E30: 1.Click 'Add to Cart' button underneath selected product - <Refer test data> 2.Validate result (Validate ER-1) | F30: MacBook | G30: Process to next page and show a successful added to cart message with a button for return to home page
A31: TC_PP_030 | B31: =_xlfn.TEXTJOIN(CHAR(10),,Scenario!A16,Scenario!C16) -> TS007 Validate the working of 'Product page' functionality | C31: Validate product comparison remove product from comparison list | D31: Open application,Open compare product page | E31: 1.Click 'Remove' button underneath selected product - <Refer test data> 2.Validate result (Validate ER-1) | F31: MacBook Air | G31: Selected product should be removed from product comparison page

Sheet Shopping Cart page
A1: Test Case ID | B1: Test Scenario | C1: Test Case Title | D1: Pre-requisites | E1: Test Steps | F1: Test Data | G1: Expected Result (ER) | H1: Actual Result | I1: Priority | J1: Result | K1: Comments
A2: TC_SC_001 | B2: =_xlfn.TEXTJOIN(CHAR(10),,Scenario!A19,Scenario!C19) -> TS010 Validate the working of 'Shopping Cart page' functionality | C2: Validate access to shopping cart page | D2: Open application, Added product to the cart | E2: 1. Click 'Shopping Cart' in header 2. Validate result (Validate ER-1) | F2: Not applicable | G2: Redirect user to 'Shopping Cart Page'
A3: TC_SC_002 | B3: =_xlfn.TEXTJOIN(CHAR(10),,Scenario!A19,Scenario!C19) -> TS010 Validate the working of 'Shopping Cart page' functionality | C3: Validate shopping cart page content - cart | D3: Open application, Added product to the cart, Open shopping cart page | E3: 1. Validate result (Validate ER-1) | F3: Not applicable | G3: Shopping cart page should show following element correctly : header, image, product name, model, quantity, unit price, total
A4: TC_SC_003 | B4: =_xlfn.TEXTJOIN(CHAR(10),,Scenario!A19,Scenario!C19) -> TS010 Validate the working of 'Shopping Cart page' functionality | C4: Validate cart functionality - change quantity of the product | D4: Open application, Added product to the cart, Open shopping cart page | E4: 1. Change quantity -<Refer test data> 2. Click refresh button next to quality 3. Validate result (Validate ER-1) | F4: Quantity : 5 | G4: Total price , Eco Tax, VAT should be updated
A5: TC_SC_004 | B5: =_xlfn.TEXTJOIN(CHAR(10),,Scenario!A19,Scenario!C19) -> TS010 Validate the working of 'Shopping Cart page' functionality | C5: Validate cart functionality - increase quantity of the product - out of stock | D5: Open application, Added product to the cart, Open shopping cart page | E5: 1. Change quantity -<Refer test data> 2. Click refresh button next to quality 3. Validate result (Validate ER-1) | F5: Quantity : 200 | G5: Should show a message "your quantity of the product is more than the current stock please lower the quantity or cancel the order"
A6: TC_SC_005 | B6: =_xlfn.TEXTJOIN(CHAR(10),,Scenario!A19,Scenario!C19) -> TS010 Validate the working of 'Shopping Cart page' functionality | C6: Validate cart functionality - decrease quantity of the product - lower than 1 | D6: Open application, Added product to the cart, Open shopping cart page | E6: 1. Change quantity -<Refer test data> 2. Click refresh button next to quality 3. Validate result (Validate ER-1) | F6: Quantity : 0 | G6: Should not accept the number 0 in quantity or remove item from cart
A7: TC_SC_006 | B7: =_xlfn.TEXTJOIN(CHAR(10),,Scenario!A19,Scenario!C19) -> TS010 Validate the working of 'Shopping Cart page' functionality | C7: Validate cart functionality - remove item | D7: Open application, Added product to the cart, Open shopping cart page | E7: 1. Click 'X' symbol next to refresh button 2. Validate result (Validate ER-1) | F7: Not applicable | G7: The product should be removed from cart
A8: TC_SC_007 | B8: =_xlfn.TEXTJOIN(CHAR(10),,Scenario!A19,Scenario!C19) -> TS010 Validate the working of 'Shopping Cart page' functionality | C8: Validate shopping cart page content - option | D8: Open application, Added product to the cart, Open shopping cart page | E8: 1. Validate result (Validate ER-1) | F8: Not applicable | G8: User can use these following option : apply coupon, estimating shipping & taxes, use gift certificate
A9: TC_SC_008 | B9: =_xlfn.TEXTJOIN(CHAR(10),,Scenario!A19,Scenario!C19) -> TS010 Validate the working of 'Shopping Cart page' functionality | C9: Validate coupon tab show | D9: Open application, Added product to the cart, Open shopping cart page | E9: 1. Click on 'Use coupon code' (Validate ER-1) | F9: Not applicable | G9: 1. coupon tab should appear
A10: TC_SC_009 | B10: =_xlfn.TEXTJOIN(CHAR(10),,Scenario!A19,Scenario!C19) -> TS010 Validate the working of 'Shopping Cart page' functionality | C10: Validate coupon tab hidden | D10: Open application, Added product to the cart, Open shopping cart page, Open a coupon tab | E10: 1. Click on 'Use coupon code' (Validate ER-1) | F10: Not applicable | G10: 1. coupon tab should hidden
A11: TC_SC_010 | B11: =_xlfn.TEXTJOIN(CHAR(10),,Scenario!A19,Scenario!C19) -> TS010 Validate the working of 'Shopping Cart page' functionality | C11: Validate valid coupon | D11: Open application, Added product to the cart, Open shopping cart page, Open a coupon tab | E11: 1. Enter coupon code -<Refer test data> 2. Validate result (Validate ER-1) | F11: HNY2026 | G11: Coupon code should be accepct and calculated discount should display
A12: TC_SC_011 | B12: =_xlfn.TEXTJOIN(CHAR(10),,Scenario!A19,Scenario!C19) -> TS010 Validate the working of 'Shopping Cart page' functionality | C12: Validate invalid coupon - expired | D12: Open application, Added product to the cart, Open shopping cart page, Open a coupon tab | E12: 1. Click on 'Use coupon code' (Validate ER-1) 2. Enter coupon code -<Refer test data> 3. Validate result (Validate ER-1) | F12: HNY2000 | G12: Should display message "this coupon code is expired"
A13: TC_SC_012 | B13: =_xlfn.TEXTJOIN(CHAR(10),,Scenario!A19,Scenario!C19) -> TS010 Validate the working of 'Shopping Cart page' functionality | C13: Validate invalid coupon - wrong coupon | D13: Open application, Added product to the cart, Open shopping cart page, Open a coupon tab | E13: 1. Click on 'Use coupon code' (Validate ER-1) 2. Enter coupon code -<Refer test data> 3. Validate result (Validate ER-1) | F13: FACEBOOK | G13: Should display message "this coupon code is invalid"
A14: TC_SC_013 | B14: =_xlfn.TEXTJOIN(CHAR(10),,Scenario!A19,Scenario!C19) -> TS010 Validate the working of 'Shopping Cart page' functionality | C14: Validate invalid coupon - boundary | D14: Open application, Added product to the cart, Open shopping cart page, Open a coupon tab | E14: 1. Click on 'Use coupon code' (Validate ER-1) 2. Enter coupon code -<Refer test data> 3. Validate result (Validate ER-1) | F14: A,Happynewyaer2026 | G14: Should not accept coupon that not in boundary ( 5-10 characters)
A15: TC_SC_014 | B15: =_xlfn.TEXTJOIN(CHAR(10),,Scenario!A19,Scenario!C19) -> TS010 Validate the working of 'Shopping Cart page' functionality | C15: Validate estimate & shipping taxes show | D15: Open application, Added product to the cart, Open shopping cart page | E15: 1. Click on 'Estimate Shipping & Taxes' 2. Validate result (Validate ER-1) | F15: Not applicable | G15: 'Estimate Shipping & Taxes' should appear below the tab, should contain following details : Country input, Region input, Post code input and Get Quotes button.
A16: TC_SC_015 | B16: =_xlfn.TEXTJOIN(CHAR(10),,Scenario!A19,Scenario!C19) -> TS010 Validate the working of 'Shopping Cart page' functionality | C16: Validate estimate & shipping taxes hidden | D16: Open application, Added product to the cart, Open shopping cart page, Open estimate & shipping taxes tab | E16: 1. Click on 'Estimate Shipping & Taxes' 2. Validate result (Validate ER-1) | F16: Not applicable | G16: The tab should hidden
A17: TC_SC_016 | B17: =_xlfn.TEXTJOIN(CHAR(10),,Scenario!A19,Scenario!C19) -> TS010 Validate the working of 'Shopping Cart page' functionality | C17: Validate country selection - default | D17: Open application, Added product to the cart, Open shopping cart page, Open estimate & shipping taxes tab | E17: 1. Validate result (Validate ER-1) | F17: Not applicable | G17: Default country should be 'United Kingdom'
A18: TC_SC_017 | B18: =_xlfn.TEXTJOIN(CHAR(10),,Scenario!A19,Scenario!C19) -> TS010 Validate the working of 'Shopping Cart page' functionality | C18: Validate country selection | D18: Open application, Added product to the cart, Open shopping cart page, Open estimate & shipping taxes tab | E18: 1. Click dropdown button on Country tab (Validate ER-1) 2. Select country - <Refer test data> 3. Validate result (Validate ER-2) | F18: Thailand | G18: 1. Country list should appear in dropdown selection format 2. Selected country should show in country tab
A19: TC_SC_018 | B19: =_xlfn.TEXTJOIN(CHAR(10),,Scenario!A19,Scenario!C19) -> TS010 Validate the working of 'Shopping Cart page' functionality | C19: Validate country selection - required field | D19: Open application, Added product to the cart, Open shopping cart page, Open estimate & shipping taxes tab | E19: 1. Select country -<Refer test data> 2. Click 'Get Quotes' button 3. Validate result (Validate ER-1) | F19: Country : Please Select | G19: Country should not be possible to send null option,Country tab should be required field
A20: TC_SC_019 | B20: =_xlfn.TEXTJOIN(CHAR(10),,Scenario!A19,Scenario!C19) -> TS010 Validate the working of 'Shopping Cart page' functionality | C20: Validate 'Region/State' selection - default | D20: Open application, Added product to the cart, Open shopping cart page, Open estimate & shipping taxes tab | E20: 1.Validate result (Validate ER-1) | F20: Not applicable | G20: Default option should be --None-- due to not yet select country
A21: TC_SC_020 | B21: =_xlfn.TEXTJOIN(CHAR(10),,Scenario!A19,Scenario!C19) -> TS010 Validate the working of 'Shopping Cart page' functionality | C21: Validate 'Region/State' selection - selection list | D21: Open application, Added product to the cart, Open shopping cart page, Open estimate & shipping taxes tab | E21: 1. Select country -<Refer test data> 2. Validate result (Validate ER-1) | F21: Country : Thailand | G21: 1. All Region/State in selected country should appear on region/state drop down list
A22: TC_SC_021 | B22: =_xlfn.TEXTJOIN(CHAR(10),,Scenario!A19,Scenario!C19) -> TS010 Validate the working of 'Shopping Cart page' functionality | C22: Validate 'Region/State' selection - selection | D22: Open application, Added product to the cart, Open shopping cart page, Open estimate & shipping taxes tab, Select country | E22: 1. Select country -<Refer test data (country)> 2. Validate result (Validate ER-1) 3. Select state -<Refer test data (state/region)> 4. Validate result (Validate ER-2) | F22: Country : Thailand, Region/State : krabi | G22: 1. All Region/State in selected country should appear on region/state drop down list 2. Selected option should show in 'Region/State' tab
A23: TC_SC_022 | B23: =_xlfn.TEXTJOIN(CHAR(10),,Scenario!A19,Scenario!C19) -> TS010 Validate the working of 'Shopping Cart page' functionality | C23: Validate 'Region/State' selection - invalid | D23: Open application, Added product to the cart, Open shopping cart page, Open estimate & shipping taxes tab, Select country | E23: 1. Select country -<Refer test data (country)> 2. Validate result (Validate ER-1) 3. Select state -<Refer test data (state/region)> 4. Validate result (Validate ER-2,ER-3,ER-4) | F23: Country : Thailand Region/State : Please Select | G23: 1. All Region/State in selected country should appear on region/state drop down list 2. Region/state should not be possible to send null option 3. Region/state tab should be required field 4. Error message 'Please select region / state !' should appear
A24: TC_SC_023 | B24: =_xlfn.TEXTJOIN(CHAR(10),,Scenario!A19,Scenario!C19) -> TS010 Validate the working of 'Shopping Cart page' functionality | C24: Validate 'Post Code' data - valid | D24: Open application, Added product to the cart, Open shopping cart page, Open estimate & shipping taxes tab | E24: 1. Enter post code -<Refer test data> 2. Click 'Get Quotes' button 3. Validate result (Validate ER-1) | F24: Post code : 13000 | G24: 1. Should accept entered post code
A25: TC_SC_024 | B25: =_xlfn.TEXTJOIN(CHAR(10),,Scenario!A19,Scenario!C19) -> TS010 Validate the working of 'Shopping Cart page' functionality | C25: Validate 'Post Code' data - invalid (not usable in any format) | D25: Open application, Added product to the cart, Open shopping cart page, Open estimate & shipping taxes tab | E25: 1. Enter post code -<Refer test data> 2. Click 'Get Quotes' button 3. Validate result (Validate ER-1) | F25: Post code : abcdefg | G25: 1. Should show error message 'Please input valid post code'
A26: TC_SC_025 | B26: =_xlfn.TEXTJOIN(CHAR(10),,Scenario!A19,Scenario!C19) -> TS010 Validate the working of 'Shopping Cart page' functionality | C26: Validate 'Post Code' data - invalid (usable in other region but not selected one) | D26: Open application, Added product to the cart, Open shopping cart page, Open estimate & shipping taxes tab | E26: 1. Enter post code -<Refer test data> 2. Click 'Get Quotes' button 3. Validate result (Validate ER-1) | F26: Post code : A1A | G26: 1. Should show error message 'Please input valid post code'
A27: TC_SC_026 | B27: =_xlfn.TEXTJOIN(CHAR(10),,Scenario!A19,Scenario!C19) -> TS010 Validate the working of 'Shopping Cart page' functionality | C27: Validate estimate & shipping taxes calculation | D27: Open application, Added product to the cart, Open shopping cart page, Open estimate & shipping taxes tab | E27: 1. Select country,region/state,postcode -<Refer test data> 2. Click 'Get Quotes' button 3. Validate result (Validate ER-1) | F27: Country : Thailand, Region/State : Bangkok, Post code : 10230 | G27: 1. Show calculated shipping fee & method available
A28: TC_SC_027 | B28: =_xlfn.TEXTJOIN(CHAR(10),,Scenario!A19,Scenario!C19) -> TS010 Validate the working of 'Shopping Cart page' functionality | C28: Validate shipping method selection | D28: Open application, Added product to the cart, Open shopping cart page, Open estimate & shipping taxes tab, calculated shipping location | E28: 1. Select shipping method -<Refer test data> 2. Click 'Apply Shipping' button | F28: Flat Shipping Rate - $5.00 | G28: 1. Shipping fee should appear and calculated in price calculation
A29: TC_SC_028 | B29: =_xlfn.TEXTJOIN(CHAR(10),,Scenario!A19,Scenario!C19) -> TS010 Validate the working of 'Shopping Cart page' functionality | C29: Validate use gift certificate shown | D29: Open application, Added product to the cart, Open shopping cart page | E29: 1. Click on 'Use Gift Certificate' 2. Validate result (Validate ER-1) | F29: Not applicable | G29: 1. gift certificate input tab should appear below 'Use Gift Certificate'
A30: TC_SC_029 | B30: =_xlfn.TEXTJOIN(CHAR(10),,Scenario!A19,Scenario!C19) -> TS010 Validate the working of 'Shopping Cart page' functionality | C30: Validate use gift certificate hidden | D30: Open application, Added product to the cart, Open shopping cart page, Open gift certificate tab | E30: 1. Click on 'Use Gift Certificate' 2. Validate result (Validate ER-1) | F30: Not applicable | G30: 1. gift certificate input tab should disappear
A31: TC_SC_030 | B31: =_xlfn.TEXTJOIN(CHAR(10),,Scenario!A19,Scenario!C19) -> TS010 Validate the working of 'Shopping Cart page' functionality | C31: Validate valid gift certificate | D31: Open application, Added product to the cart, Open shopping cart page, Open gift certificate tab | E31: 1. Input gift certificate 2. Validate result (Validate ER-1) | F31: MyGift2026 | G31: 1. code accept and show result (discount / free item ) on shopping cart / calculation tab
A32: TC_SC_031 | B32: =_xlfn.TEXTJOIN(CHAR(10),,Scenario!A19,Scenario!C19) -> TS010 Validate the working of 'Shopping Cart page' functionality | C32: Validate invalid gift certificate | D32: Open application, Added product to the cart, Open shopping cart page, Open gift certificate tab | E32: 1. Input gift certificate 2. Validate result (Validate ER-1) | F32: MyGift 2555,null,A | G32: Should show message ' Warning: Gift Certificate is either invalid or the balance has been used up!'
A33: TC_SC_032 | B33: =_xlfn.TEXTJOIN(CHAR(10),,Scenario!A19,Scenario!C19) -> TS010 Validate the working of 'Shopping Cart page' functionality | C33: Validate shopping cart page content - detailed price | D33: Open application, Added product to the cart, Open shopping cart page | E33: 1. Validate result (Validate ER-1) | F33: Not applicable | G33: User can confirm the price details on the item which show under the extra option which contain: Sub-total, Eco Tax, Vat, Total
A34: TC_SC_033 | B34: =_xlfn.TEXTJOIN(CHAR(10),,Scenario!A19,Scenario!C19) -> TS010 Validate the working of 'Shopping Cart page' functionality | C34: Validate shopping cart page content - detailed price calculation | D34: Open application, Added product to the cart, Open shopping cart page | E34: 1. Validate result (Validate ER-1) | F34: Not applicable | G34: Result of detailed price should shown correctly
A35: TC_SC_034 | B35: =_xlfn.TEXTJOIN(CHAR(10),,Scenario!A19,Scenario!C19) -> TS010 Validate the working of 'Shopping Cart page' functionality | C35: Validate 'Continue Shopping' button | D35: Open application, Added product to the cart, Open shopping cart page | E35: 1. Click on 'Continue Shopping' button 2. Validate result (Validate ER-1) | F35: Not applicable | G35: Should redirect user to home page / all record item should still in cart
A36: TC_SC_035 | B36: =_xlfn.TEXTJOIN(CHAR(10),,Scenario!A19,Scenario!C19) -> TS010 Validate the working of 'Shopping Cart page' functionality | C36: Validate 'Checkout' button | D36: Open application, Added product to the cart, Open shopping cart page | E36: 1. Click on 'Checkout' button 2. Validate result (Validate ER-1) | F36: Not applicable | G36: Should redirect user to checkout page

Sheet AddToCart
A1: Test Case ID | B1: Test Scenario | C1: Test Case Title | D1: Pre-requisites | E1: Test Steps | F1: Test Data | G1: Expected Result (ER) | H1: Actual Result | I1: Priority | J1: Result | K1: Comments
A2: TC_ATC_001 | B2: =_xlfn.TEXTJOIN(CHAR(10),,Scenario!$A$17,Scenario!$C$17) -> TS008 Validate the working of 'Add to cart' functionality | C2: Add to cart - home page | D2: Open Application | E2: 1. Click cart button on product -<Refer test data> 2. Validate result (ER-1) | F2: product : iPhone
A3: TC_ATC_002 | B3: =_xlfn.TEXTJOIN(CHAR(10),,Scenario!$A$17,Scenario!$C$17) -> TS008 Validate the working of 'Add to cart' functionality | C3: Add to cart - main category | D3: Open Application | E3: 1. Click on category -<Refer test data : category> 2. Click cart button on product -<Refer test data : product> 3. Validate result (ER-1) | F3: Category : desktop Product : HP LP3065
A4: TC_ATC_003 | B4: =_xlfn.TEXTJOIN(CHAR(10),,Scenario!$A$17,Scenario!$C$17) -> TS008 Validate the working of 'Add to cart' functionality | C4: Add to cart - sub category | D4: Open Application | E4: 1. Click on category -<Refer test data : category> 2. Click on sub-category -<Refer test data : sub category> 3. Click cart button on product -<Refer test data : product> 4. Validate result (ER-1) | F4: Category : desktop Sub category : Mac product : iMac
A5: TC_ATC_004 | B5: =_xlfn.TEXTJOIN(CHAR(10),,Scenario!$A$17,Scenario!$C$17) -> TS008 Validate the working of 'Add to cart' functionality | C5: Add to cart - product comparison | D5: Open Application,added product(s) to comparison list | E5: 1. Click cart button on product in product comparison page 2. Validate result (ER-1) | F5: Product : any product on comparison list
A6: TC_ATC_005 | B6: =_xlfn.TEXTJOIN(CHAR(10),,Scenario!$A$17,Scenario!$C$17) -> TS008 Validate the working of 'Add to cart' functionality | C6: Add to cart - wish list | D6: Open Application,added product(s) to wish list | E6: 1. Open wish list page 2. Click cart button on product in wish list (ER-1) | F6: Product : any product on wish list
A7: TC_ATC_006 | B7: =_xlfn.TEXTJOIN(CHAR(10),,Scenario!$A$17,Scenario!$C$17) -> TS008 Validate the working of 'Add to cart' functionality | C7: Add to cart - brands | D7: Open Application | E7: 1. Select brand -<Refer test data : brand> 2. Click cart button on product -<Refer test data : product> | F7: Brand : apple Product : iMac
A8: TC_ATC_007 | B8: =_xlfn.TEXTJOIN(CHAR(10),,Scenario!$A$17,Scenario!$C$17) -> TS008 Validate the working of 'Add to cart' functionality | C8: Add to cart - search result | D8: Open Application | E8: 1. Input search criteria -<Refer test data : criteria> 2. Click cart button on product -<Refer test data : product > | F8: Criteria : iPhone Product : iPhone
A9: TC_ATC_008 | B9: =_xlfn.TEXTJOIN(CHAR(10),,Scenario!$A$17,Scenario!$C$17) -> TS008 Validate the working of 'Add to cart' functionality | C9: Add to cart - display section | D9: Open Application | E9: 1. Select product from display section -<Refer test data : display> 2. Click cart button on product -<Refer test data : product> 3. Validate Result (ER-1) | F9: display product : Samsung Galaxy Tab 10.1 product : Samsung Galaxy Tab 10.1
A10: TC_ATC_009 | B10: =_xlfn.TEXTJOIN(CHAR(10),,Scenario!$A$17,Scenario!$C$17) -> TS008 Validate the working of 'Add to cart' functionality | C10: Add to cart - featured | D10: Open Application | E10: 1. Click cart button on product show in featured product -<Refer test data : product> 2. Validate Result (ER-1) | F10: product : MacBook
A11: TC_ATC_010 | B11: =_xlfn.TEXTJOIN(CHAR(10),,Scenario!$A$17,Scenario!$C$17) -> TS008 Validate the working of 'Add to cart' functionality | C11: Add to cart - message - success | D11: Open Application | E11: 1. Click cart button on any product -<Refer test data> 2. Validate result (ER-1) | F11: product : any | G11: Should show message " Success: You have added [product name] to your shopping cart!"
A12: TC_ATC_011 | B12: =_xlfn.TEXTJOIN(CHAR(10),,Scenario!$A$17,Scenario!$C$17) -> TS008 Validate the working of 'Add to cart' functionality | C12: Add to cart - message - out of stock | D12: Open Application | E12: 1. Click cart button on out of stock product -<Refer test data> 2. Validate result (ER-1) | F12: product : iPhone | G12: Should show message "This product is out of stock" | H12: Show message "Success: You have added [product name] to your shopping cart!" | J12: defect

Sheet WishList
A1: Test Case ID | B1: Test Scenario | C1: Test Case Title | D1: Pre-requisites | E1: Test Steps | F1: Test Data | G1: Expected Result (ER) | H1: Actual Result | I1: Priority | J1: Result | K1: Comments
A2: TC_WL_001 | B2: =_xlfn.TEXTJOIN(CHAR(10),,Scenario!$A$18,Scenario!$C$18) -> TS009 Validate the working of 'Wish List' option | C2: Wish list - success | D2: Open Application, logged in | E2: 1. Click hearth symbol on product -<Refer test data> 2. Validate result (ER-1) | F2: item : iPhone | G2: Show message " Success: You have added iPhone to your wish list!" | H2: Show message " Success: You have added iPhone to your wish list!"
A3: TC_WL_002 | B3: =_xlfn.TEXTJOIN(CHAR(10),,Scenario!$A$18,Scenario!$C$18) -> TS009 Validate the working of 'Wish List' option | C3: Wish list - not logged in | D3: Open Application, not logged in | E3: 1. Click hearth symbol on product -<Refer test data> 2. Validate result (ER-1) | F3: item : iPhone | G3: Show message " You must login or create an account to save Apple Cinema 30" to your wish list!" | H3: Show message " You must login or create an account to save Apple Cinema 30" to your wish list!"
A4: TC_WL_003 | B4: =_xlfn.TEXTJOIN(CHAR(10),,Scenario!$A$18,Scenario!$C$18) -> TS009 Validate the working of 'Wish List' option | C4: Wish list - duplicate | D4: Open Application, logged in,already added item on wish list | E4: 1. Click hearth symbol on product that is already on wish list -<Refer test data> 2. Validate result (ER-1) | F4: item : iPhone | G4: Should show message "This item is already in your wish list" | H4: Show message " Success: You have added iPhone to your wish list!" | J4: defect
A5: TC_WL_004 | B5: =_xlfn.TEXTJOIN(CHAR(10),,Scenario!$A$18,Scenario!$C$18) -> TS009 Validate the working of 'Wish List' option | C5: Wish list page - access | D5: Open Application, logged in | E5: 1. Click wish list on header 2. Validate result (ER-1) | F5: Not applicable | G5: Redirect user to wish list page | H5: Redirect user to wish list page
A6: TC_WL_005 | B6: =_xlfn.TEXTJOIN(CHAR(10),,Scenario!$A$18,Scenario!$C$18) -> TS009 Validate the working of 'Wish List' option | C6: Wish list page - empty | D6: Open Application, logged in | E6: 1. Click wish list on header 2. Validate result (ER-1) | F6: Not applicable | G6: Should show message "Your wish list is empty" | H6: show correct message
A7: TC_WL_006 | B7: =_xlfn.TEXTJOIN(CHAR(10),,Scenario!$A$18,Scenario!$C$18) -> TS009 Validate the working of 'Wish List' option | C7: Wish list page - have item(s) | D7: Open Application, logged in,already added item on wish list | E7: 1. Click wish list on header 2. Validate result (ER-1) | F7: Not applicable | G7: Should show item detail on wish list contain these information : image, product name, model, stock, unit price, action(with add to cart and remove button), continue button, account navigation feature on right side | H7: show correct information
A8: TC_WL_007 | B8: =_xlfn.TEXTJOIN(CHAR(10),,Scenario!$A$18,Scenario!$C$18) -> TS009 Validate the working of 'Wish List' option | C8: Wish list - remove item | D8: Open Application, logged in,already added item on wish list, enter wish list page | E8: 1. Click 'X' mark on action tab of selected item -<Refer test data> 2. Validate result (ER-1) | F8: item : iPhone | G8: selected item should removed from wish list | H8: selected item is removed from wish list
A9: TC_WL_008 | B9: =_xlfn.TEXTJOIN(CHAR(10),,Scenario!$A$18,Scenario!$C$18) -> TS009 Validate the working of 'Wish List' option | C9: Wish list - continue button | D9: Open Application, logged in,already added item on wish list, enter wish list page | E9: 1. Click continue button 2. Validate result (ER-1) | F9: Not applicable | G9: Should redirect to account page | H9: Redirect user to account page
A10: TC_WL_009 | B10: =_xlfn.TEXTJOIN(CHAR(10),,Scenario!$A$18,Scenario!$C$18) -> TS009 Validate the working of 'Wish List' option | C10: Wish list - add wish list item to cart | D10: Open Application, logged in,already added item on wish list, enter wish list page | E10: 1. Click cart icon on action tab of selected item -<Refer test data> 2. Validate result (ER-1) | F10: item : iPhone | G10: selected item should added to cart
A11: TC_WL_010 | B11: =_xlfn.TEXTJOIN(CHAR(10),,Scenario!$A$18,Scenario!$C$18) -> TS009 Validate the working of 'Wish List' option | C11: Wish list - add out of stock wish list item to cart | D11: Open Application, logged in,already added item on wish list, enter wish list page | E11: 1. Click cart icon on action tab of selected item -<Refer test data> 2. Validate result (ER-1) | F11: item : iPhone | G11: Should show message "This item is out of stock" | H11: Show message " Success: You have added iPhone to your shopping cart! " , text "Warning: Undefined array key "stock_status" in /var/www/opencart.com/web/catalog/controller/account/wishlist.php on line 98Warning: Undefined array key "stock_status" in /var/www/opencart.com/web/catalog/controller/account/wishlist.php on line 98" visible under my wish list | J11: defect

Sheet Currency
A1: Test Case ID | B1: Test Scenario | C1: Test Case Title | D1: Pre-requisites | E1: Test Steps | F1: Test Data | G1: Expected Result (ER) | H1: Actual Result | I1: Priority | J1: Result | K1: Comments
A2: TC_CF_001 | B2: =_xlfn.TEXTJOIN(CHAR(10),,Scenario!A42,Scenario!C42) -> TS033 Validate the Application functionality for different currency | C2: Change currency to USD | D2: Open https://demo.opencart.com/ | E2: 1. Click Currency dropdown on header tab 2. Select prefered currency | F2: USD($) | G2: The price of the product will change to selected currency
A3: TC_CF_002 | B3: =_xlfn.TEXTJOIN(CHAR(10),,Scenario!A42,Scenario!C42) -> TS033 Validate the Application functionality for different currency | C3: Available currency | D3: Open https://demo.opencart.com/ | E3: 1. Click Currency dropdown on header tab | F3: No Applicable | G3: The available currency will show in dropdown list ($ for USD, € for EUR)

Sheet Checkout
A1: Test Case ID | B1: Test Scenario | C1: Test Case Title | D1: Pre-requisites | E1: Test Steps | F1: Test Data | G1: Expected Result (ER) | H1: Actual Result | I1: Priority | J1: Result | K1: Comments
A2: TC_CO_001 | B2: =_xlfn.TEXTJOIN(CHAR(10),,Scenario!$A$21,Scenario!$C$21) -> TS012 Validate the working of 'Checkout' functionality | C2: Validate checkout - access | D2: Open application,add product to cart | E2: 1. Click checkout on header section 2. Validate result (ER-1) | F2: Not applicable
A3: TC_CO_002 | B3: =_xlfn.TEXTJOIN(CHAR(10),,Scenario!$A$21,Scenario!$C$21) -> TS012 Validate the working of 'Checkout' functionality | C3: Validate checkout with guest | D3: Open application,add product to cart, click checkout, not logged in | E3: 1. Validate result (ER-1) | F3: Not applicable | G3: 1) Will show message "If you already have an account with us, please login at the login page." above personal details section 2) have selection for register / guest checkout shown
A4: TC_CO_003 | B4: =_xlfn.TEXTJOIN(CHAR(10),,Scenario!$A$21,Scenario!$C$21) -> TS012 Validate the working of 'Checkout' functionality | C4: Validate checkout with guest (login link) | D4: Open application,add product to cart, click checkout, not logged in, select register account | E4: 1. Click login page link on mesasge 2. Validate result (ER-1) | F4: Not applicable | G4: Should navigate user to login page
A5: TC_CO_004 | B5: =_xlfn.TEXTJOIN(CHAR(10),,Scenario!$A$21,Scenario!$C$21) -> TS012 Validate the working of 'Checkout' functionality | C5: Validate create password (guest register) - valid | D5: Open application,add product to cart, click checkout, not logged in | E5: 1. Select register account checkbox 2. Enter password -<Refer test data> 3. Click continue 4. Validate result (ER-1) | F5: password : 123456 | G5: Should accept password
A6: TC_CO_005 | B6: =_xlfn.TEXTJOIN(CHAR(10),,Scenario!$A$21,Scenario!$C$21) -> TS012 Validate the working of 'Checkout' functionality | C6: Validate create password (guest register) - boundary | D6: Open application,add product to cart, click checkout, not logged in | E6: 1. Select register account checkbox 2. Enter password -<Refer test data> 3. Click continue 4. Validate result (ER-1) | F6: password : 11,ฤโ"897,over 20 characters password | G6: will show message "Only accpet password with 4-20 characters with english,number and special characters only " if not in criteria
A7: TC_CO_006 | B7: =_xlfn.TEXTJOIN(CHAR(10),,Scenario!$A$21,Scenario!$C$21) -> TS012 Validate the working of 'Checkout' functionality | C7: Validate create password (guest register) - required field | D7: Open application,add product to cart, click checkout, not logged in | E7: 1. Select register account checkbox 2. Leave password input empty 3. Click continue 4. Validate result (ER-1) | F7: Not applicable | G7: If left input empty system should show this field is required field should have " * " display next to create password text
A8: TC_CO_007 | B8: =_xlfn.TEXTJOIN(CHAR(10),,Scenario!$A$21,Scenario!$C$21) -> TS012 Validate the working of 'Checkout' functionality | C8: Validate create password (guest register) - hidden input | D8: Open application,add product to cart, click checkout, not logged in | E8: 1. Select register account checkbox 2. Enter password -<Refer test data> 3. Validate result (ER-1) | F8: password : 123456789 | G8: This field input should display in hidden (******)
A9: TC_CO_008 | B9: =_xlfn.TEXTJOIN(CHAR(10),,Scenario!$A$21,Scenario!$C$21) -> TS012 Validate the working of 'Checkout' functionality | C9: Validate guest register - additional section | D9: Open application,add product to cart, click checkout, not logged in | E9: 1. Select register account checkbox 2. Validate result (ER-1) | F9: Not applicable | G9: Should show password section & additional option for privacy policy
A10: TC_CO_009 | B10: =_xlfn.TEXTJOIN(CHAR(10),,Scenario!$A$21,Scenario!$C$21) -> TS012 Validate the working of 'Checkout' functionality | C10: Validate guest register - email duplicate | D10: Open application,add product to cart, click checkout, not logged in | E10: 1. Select register account checkbox 2. Enter email -<Refer test data> 3. Click continue 4. Validate result (ER-1) | F10: test@gmail.com | G10: Should show message "This email is already used, please login"
A11: TC_CO_010 | B11: =_xlfn.TEXTJOIN(CHAR(10),,Scenario!$A$21,Scenario!$C$21) -> TS012 Validate the working of 'Checkout' functionality | C11: Validate guest register - switch to guest checkout | D11: User on checkout page, selected register account option | E11: 1. Select guest checkout 2. Validate result (ER-1) | F11: Not applicable | G11: Password section & privacy policy option should disappear
A12: TC_CO_011 | B12: =_xlfn.TEXTJOIN(CHAR(10),,Scenario!$A$21,Scenario!$C$21) -> TS012 Validate the working of 'Checkout' functionality | C12: Validate switch from guest register to guest checkout should not has any required field error from guest register | D12: User on checkout page, selected register account option | E12: 1. Select guest checkout 2. Click continue 3. Validate result | F12: Not applicable | G12: Should not have error message from password & privacy policy
A13: TC_CO_012 | B13: =_xlfn.TEXTJOIN(CHAR(10),,Scenario!$A$21,Scenario!$C$21) -> TS012 Validate the working of 'Checkout' functionality | C13: Validate checkout with member | D13: Open application,add product to cart, click checkout, logged in | E13: 1. Validate result (ER-1) | F13: Not applicable | G13: Only show payment method, comment and order details
A14: TC_CO_013 | B14: =_xlfn.TEXTJOIN(CHAR(10),,Scenario!$A$21,Scenario!$C$21) -> TS012 Validate the working of 'Checkout' functionality | C14: Validate personal details - first name valid | D14: Open application,enter checkout page, not logged in | E14: 1. Enter firstname -<Refer test data> 2. Click continue 3. Validate result (ER-1) | F14: Mike | G14: Should accept first name
... A37: TC_CO_039 | B37: =_xlfn.TEXTJOIN(CHAR(10),,Scenario!$A$21,Scenario!$C$21) -> TS012 Validate the working of 'Checkout' functionality | C37: Validate address - post code - empty | D37: Open application,enter checkout page, not logged in | E37: 1. Leave post code empty 2. Click continue 3. Validate result (ER-1) | F37: Not applicable | G37: Should show message "Please in put post code" , have " * " mark show on postcode
B38: =_xlfn.TEXTJOIN(CHAR(10),,Scenario!$A$21,Scenario!$C$21) -> TS012 Validate the working of 'Checkout' functionality | C38: Validate address - post code - invalid | D38: Open application,enter checkout page, not logged in | E38: 1. Input post code -<Refer test data> 2. Click continue 3. Validate result (ER-1) | F38: Post code : !#$)@) | G38: Should only accpet valid post code : only number, english character with number for some country
A39: TC_CO_040 | B39: =_xlfn.TEXTJOIN(CHAR(10),,Scenario!$A$21,Scenario!$C$21) -> TS012 Validate the working of 'Checkout' functionality | C39: Validate address - country - valid | D39: Open application,enter checkout page, not logged in | E39: 1. Click dropdown country list 2. Select country from list 3. Validate result (ER-1) | F39: Country : thailand | G39: Selected country should appear as selected on country tab
A40: TC_CO_041 | B40: =_xlfn.TEXTJOIN(CHAR(10),,Scenario!$A$21,Scenario!$C$21) -> TS012 Validate the working of 'Checkout' functionality | C40: Validate address - country - required field | D40: Open application,enter checkout page, not logged in | E40: 1. Leave country as --Please select -- 2. Click continue 3. Validate result (ER-1) | F40: Country : --Please select -- | G40: Should show message "Please select country"
A41: TC_CO_043 | B41: =_xlfn.TEXTJOIN(CHAR(10),,Scenario!$A$21,Scenario!$C$21) -> TS012 Validate the working of 'Checkout' functionality | C41: Validate address - region/state - country selected | D41: Open application,enter checkout page, not logged in, selected country | E41: 1. Click region/state dropdown list 2. Validate result (ER-1) | F41: Not applicable | G41: Should show region/state list based on selected country
A42: TC_CO_044 | B42: =_xlfn.TEXTJOIN(CHAR(10),,Scenario!$A$21,Scenario!$C$21) -> TS012 Validate the working of 'Checkout' functionality | C42: Validate address - region/state - country not selected | D42: Open application,enter checkout page, not logged in | E42: 1. Click region/state dropdown list 2. Validate result (ER-1) | F42: Not applicable | G42: Should not selectable | H42: Selectable with --Please select -- and --None-- option
A43: TC_CO_045 | B43: =_xlfn.TEXTJOIN(CHAR(10),,Scenario!$A$21,Scenario!$C$21) -> TS012 Validate the working of 'Checkout' functionality | C43: Validate address - region/state - required field | D43: Open application,enter checkout page, not logged in | E43: 1. Leave Region/state at --Please Select-- or --None-- 2. Validate result (ER-1) | F43: Region/State : --Please select-- , --None-- | G43: Should show message "Please select region/state" and have "*" mark visible
A44: TC_CO_046 | B44: =_xlfn.TEXTJOIN(CHAR(10),,Scenario!$A$21,Scenario!$C$21) -> TS012 Validate the working of 'Checkout' functionality | C44: Validate payment methods - available | D44: Open application,enter checkout page | E44: 1. Click choose button on right side of payment field 2. Validate result (ER-1) | F44: Not applicable | G44: Should show available payment method | H44: guess :Nothing happen member : "No Payment options are available. Please contact us for assistance!"
A45: TC_CO_047 | B45: =_xlfn.TEXTJOIN(CHAR(10),,Scenario!$A$21,Scenario!$C$21) -> TS012 Validate the working of 'Checkout' functionality | C45: Validate payment methods - disable | D45: Open application,enter checkout page | E45: 1. Click choose button on right side of payment field 2. Validate result (ER-1) | F45: Kbank | G45: disabled(temporary) payment method should not selectable or not in the list
A46: TC_CO_048 | B46: =_xlfn.TEXTJOIN(CHAR(10),,Scenario!$A$21,Scenario!$C$21) -> TS012 Validate the working of 'Checkout' functionality | C46: Validate payment methods - error | D46: Open application,enter checkout page | E46: 1. Click choose button on right side of payment field 2. Validate result (ER-1) | F46: Not applicable | G46: Show message " No Payment options are available. Please contact us for assistance!"
A47: TC_CO_049 | B47: =_xlfn.TEXTJOIN(CHAR(10),,Scenario!$A$21,Scenario!$C$21) -> TS012 Validate the working of 'Checkout' functionality | C47: Validate payment methods - error - contact us link | D47: Open application,enter checkout page,payment error | E47: 1. Click contact us link on payment error message 2. Validate result (ER-1) | F47: Not applicable | G47: Should navigate user to contact us page
A48: TC_CO_050 | B48: =_xlfn.TEXTJOIN(CHAR(10),,Scenario!$A$21,Scenario!$C$21) -> TS012 Validate the working of 'Checkout' functionality | C48: Validate payment methods - select | D48: Open application,enter checkout page | E48: 1. Click choose button on right side of payment field 2. Select method -<refer test data>- 3. Validate result (ER-1) | F48: Visa | G48: Should update input to match selected method for enter payment information
A49: TC_CO_051 | B49: =_xlfn.TEXTJOIN(CHAR(10),,Scenario!$A$21,Scenario!$C$21) -> TS012 Validate the working of 'Checkout' functionality | C49: Validate payment methods - required field | D49: Open application,enter checkout page | E49: 1. Leave payment method empty 2. Click continue | F49: Not applicable | G49: Should show message "Payment detail is required" | H49: Show message "Customer required"
A50: TC_CO_052 | B50: =_xlfn.TEXTJOIN(CHAR(10),,Scenario!$A$21,Scenario!$C$21) -> TS012 Validate the working of 'Checkout' functionality | C50: Validate order comment - default | D50: Open application,enter checkout page | E50: 1. Validate result (ER-1) | F50: Not applicable | G50: Order comment should place below payment method and not a required field
A51: TC_CO_053 | B51: =_xlfn.TEXTJOIN(CHAR(10),,Scenario!$A$21,Scenario!$C$21) -> TS012 Validate the working of 'Checkout' functionality | C51: Validate order comment - empty | D51: Open application,enter checkout page | E51: 1. Leave comment empty 2. Validate result (ER-1) | F51: Not applicable | G51: Order commnet should accept empty input
A52: TC_CO_054 | B52: =_xlfn.TEXTJOIN(CHAR(10),,Scenario!$A$21,Scenario!$C$21) -> TS012 Validate the working of 'Checkout' functionality | C52: Validate order comment - valid | D52: Open application,enter checkout page | E52: 1. Input comment 2. Validate result (ER-1) | F52: text : hello | G52: Should show message "comment added"
A53: TC_CO_055 | B53: =_xlfn.TEXTJOIN(CHAR(10),,Scenario!$A$21,Scenario!$C$21) -> TS012 Validate the working of 'Checkout' functionality | C53: Validate order comment - boundary | D53: Open application,enter checkout page | E53: 1. Input comment 2. Validate result (ER-1) | F53: Valid : 123456abcd Invalid : over 256 characters text or unsupport language | G53: Only accept english and number text which not over 256 characters
A54: TC_CO_056 | B54: =_xlfn.TEXTJOIN(CHAR(10),,Scenario!$A$21,Scenario!$C$21) -> TS012 Validate the working of 'Checkout' functionality | C54: Validate billing details - default | D54: Open application,enter checkout page | E54: 1. Validate result (ER-1) | F54: Not applicable | G54: Billing detail should split in to two main section 1. product detail which contain quantity,product name, total 2. detailed price which contain sub-total,eco tax, vat, total
A55: TC_CO_057 | B55: =_xlfn.TEXTJOIN(CHAR(10),,Scenario!$A$21,Scenario!$C$21) -> TS012 Validate the working of 'Checkout' functionality | C55: Validate billing details - item calculation | D55: Open application,enter checkout page | E55: 1. Validate result (ER-1) | F55: Not applicable | G55: Item calculation should show correct price for total number of item(s)
A56: TC_CO_058 | B56: =_xlfn.TEXTJOIN(CHAR(10),,Scenario!$A$21,Scenario!$C$21) -> TS012 Validate the working of 'Checkout' functionality | C56: Validate billing details - detail price calculation - overall | D56: Open application,enter checkout page | E56: 1. Validate result (ER-1) | F56: Not applicable | G56: detail price should contain eco tax, vat, total
A57: TC_CO_059 | B57: =_xlfn.TEXTJOIN(CHAR(10),,Scenario!$A$21,Scenario!$C$21) -> TS012 Validate the working of 'Checkout' functionality | C57: Validate billing details - detail price calculation - eco tax | D57: Open application,enter checkout page | E57: 1. Validate result (ER-1) | F57: Not applicable | G57: Eco tax should only calculated from eco taxable product
A58: TC_CO_060 | B58: =_xlfn.TEXTJOIN(CHAR(10),,Scenario!$A$21,Scenario!$C$21) -> TS012 Validate the working of 'Checkout' functionality | C58: Validate billing details - detail price calculation - vat | D58: Open application,enter checkout page | E58: 1. Validate result (ER-1) | F58: Not applicable | G58: vat should show correctly
A59: TC_CO_061 | B59: =_xlfn.TEXTJOIN(CHAR(10),,Scenario!$A$21,Scenario!$C$21) -> TS012 Validate the working of 'Checkout' functionality | C59: Validate billing details - detail price calculation - total | D59: Open application,enter checkout page | E59: 1. Validate result (ER-1) | F59: Not applicable | G59: total price should match sum of total product price
A60: TC_CO_062 | B60: =_xlfn.TEXTJOIN(CHAR(10),,Scenario!$A$21,Scenario!$C$21) -> TS012 Validate the working of 'Checkout' functionality | C60: Validate delivery details - same address as billing address | D60: Open application,enter checkout page, enter billing details
A61: TC_CO_063 | B61: =_xlfn.TEXTJOIN(CHAR(10),,Scenario!$A$21,Scenario!$C$21) -> TS012 Validate the working of 'Checkout' functionality | C61: Validate delivery details different address for delivery | D61: Open application,enter checkout page, enter billing details
A62: TC_CO_064 | B62: =_xlfn.TEXTJOIN(CHAR(10),,Scenario!$A$21,Scenario!$C$21) -> TS012 Validate the working of 'Checkout' functionality | C62: Validate delivery details not selected | D62: Open application,enter checkout page, enter billing details
A63: TC_CO_065 | B63: =_xlfn.TEXTJOIN(CHAR(10),,Scenario!$A$21,Scenario!$C$21) -> TS012 Validate the working of 'Checkout' functionality | C63: Validate delivery methods - valid | D63: Open application,enter checkout page, enter billing details
A64: TC_CO_066 | B64: =_xlfn.TEXTJOIN(CHAR(10),,Scenario!$A$21,Scenario!$C$21) -> TS012 Validate the working of 'Checkout' functionality | C64: Validate delivery methods - not available | D64: Open application,enter checkout page, enter billing details
A65: TC_CO_067 | B65: =_xlfn.TEXTJOIN(CHAR(10),,Scenario!$A$21,Scenario!$C$21) -> TS012 Validate the working of 'Checkout' functionality | C65: Validate delivery methods - required | D65: Open application,enter checkout page, enter billing details
A66: TC_CO_068 | B66: =_xlfn.TEXTJOIN(CHAR(10),,Scenario!$A$21,Scenario!$C$21) -> TS012 Validate the working of 'Checkout' functionality | C66: Validate confirm order | D66: Open application,enter checkout page, enter billing details,select delivery methods,select payment methods
A67: TC_CO_069 | B67: =_xlfn.TEXTJOIN(CHAR(10),,Scenario!$A$21,Scenario!$C$21) -> TS012 Validate the working of 'Checkout' functionality | C67: Validate order complete | D67: Open application,enter checkout page, enter billing details,select delivery methods,select payment methods,confirm order
A68: TC_CO_070 | B68: =_xlfn.TEXTJOIN(CHAR(10),,Scenario!$A$21,Scenario!$C$21) -> TS012 Validate the working of 'Checkout' functionality | C68: Validate order fail | D68: Open application,enter checkout page, enter billing details,select delivery methods,select payment methods,confirm order
